{
  "success": true,
  "response": {
    "content": "### 🧬 Multi-Personality Composed Response\n\n**Request**: Test NEXUS thoroughly. Write unit tests, integration tests, property-based tests. Mock dependencies, use pytest fixtures, achieve 100% coverage.\n\n**Composed Agent**: integrationmaestro + nexus-api + hunter + pythonista\n**Synergy Score**: 55%\n\n### 🎯 Trait Composition\n\n1. **systemIntegration** (integrationmaestro)\n   - Expertise: 97%\n   - Connecting disparate systems effectively\n\n2. **API Design Patterns** (nexus-api)\n   - Expertise: 94%\n   - RESTful and GraphQL API architecture design following industry best practices and standards\n\n3. **Evidence Verification** (hunter)\n   - Expertise: 93%\n   - Validates gathered intelligence and claims against observable evidence for strategic decision-making\n\n4. **Testing & Quality Assurance** (pythonista)\n   - Expertise: 93%\n   - Expert in pytest, unittest, property-based testing with hypothesis, mocking, test-driven development, and continuous integration. Understands test coverage, mutation testing, and how to write maintainable test suites. Masters fixtures, parametrization, and testing async code.\n\n5. **Testing & Quality Assurance** (pythonista)\n   - Expertise: 93%\n   - Expert in pytest, unittest, property-based testing with hypothesis, mocking, test-driven development, and continuous integration. Understands test coverage, mutation testing, and how to write maintainable test suites. Masters fixtures, parametrization, and testing async code.\n\n### 💡 Integrated Analysis\n\nThis response leverages cognitive capabilities from **4 different personalities**, creating a ⚖️ **balanced** analytical framework.\n\n**Synergy Analysis**: 55.0% compatibility\n- 🔄 Moderate synergy - diverse perspectives with some coordination needed\n\n### 🔍 Multi-Perspective Insights\n\n**integrationmaestro's systemIntegration**\n- 📊 Expertise: 97% █████████░\n- 🎯 Specializes in: integration patterns, integration strategies, middleware, ESB\n- 🔔 Activates on: `system integration`, `integrate systems`, `integration`, `connect systems`, `system connectivity`\n- 💡 Connecting disparate systems effectively\n\n**nexus-api's API Design Patterns**\n- 📊 Expertise: 94% █████████░\n- 🎯 Specializes in: API-design, REST-architecture, GraphQL-schema, OpenAPI-specification\n- 🔔 Activates on: `API`, `REST`, `GraphQL`, `endpoint`, `integration`\n- 💡 RESTful and GraphQL API architecture design following industry best practices and standards\n\n**hunter's Evidence Verification**\n- 📊 Expertise: 93% █████████░\n- 🎯 Specializes in: testing, logs, metrics, traces\n- 🔔 Activates on: `audit`, `verify`, `evidence`, `proof`, `validate-claim`\n- 💡 Validates gathered intelligence and claims against observable evidence for strategic decision-making\n\n**pythonista's Testing & Quality Assurance**\n- 📊 Expertise: 93% █████████░\n- 🎯 Specializes in: unit-testing, integration-testing, test-driven-development, pytest\n- 🔔 Activates on: `test`, `pytest`, `unittest`, `tdd`, `mock`\n- 💡 Expert in pytest, unittest, property-based testing with hypothesis, mocking, test-driven development, and continuous integration. Understands test coverage, mutation testing, and how to write maintainable test suites. Masters fixtures, parametrization, and testing async code.\n\n**pythonista's Testing & Quality Assurance**\n- 📊 Expertise: 93% █████████░\n- 🎯 Specializes in: unit-testing, integration-testing, test-driven-development, pytest\n- 🔔 Activates on: `test`, `pytest`, `unittest`, `tdd`, `mock`\n- 💡 Expert in pytest, unittest, property-based testing with hypothesis, mocking, test-driven development, and continuous integration. Understands test coverage, mutation testing, and how to write maintainable test suites. Masters fixtures, parametrization, and testing async code.\n\n### 📚 Combined Knowledge Domains (31)\n\nintegration patterns • integration strategies • middleware • ESB • integration platforms • system connectivity • integration protocols • data synchronization • integration testing • interoperability • API-design • REST-architecture\n\n*This composed agent combines the best traits from 4 personalities for optimal task execution.*\n",
    "personalityUsed": "integrationmaestro + nexus-api + hunter + pythonista",
    "composedAgent": true,
    "nexusEnhanced": true,
    "traits": [
      {
        "name": "systemIntegration",
        "personality": "integrationmaestro",
        "expertise": 97
      },
      {
        "name": "API Design Patterns",
        "personality": "nexus-api",
        "expertise": 94
      },
      {
        "name": "Evidence Verification",
        "personality": "hunter",
        "expertise": 93
      },
      {
        "name": "Testing & Quality Assurance",
        "personality": "pythonista",
        "expertise": 93
      },
      {
        "name": "Testing & Quality Assurance",
        "personality": "pythonista",
        "expertise": 93
      }
    ],
    "traitApplications": [
      "systemIntegration",
      "API Design Patterns",
      "Evidence Verification",
      "Testing & Quality Assurance",
      "Testing & Quality Assurance"
    ],
    "synergyScore": 0.55,
    "knowledgeDomains": [
      "integration patterns",
      "integration strategies",
      "middleware",
      "ESB",
      "integration platforms",
      "system connectivity",
      "integration protocols",
      "data synchronization",
      "integration testing",
      "interoperability",
      "API-design",
      "REST-architecture",
      "GraphQL-schema",
      "OpenAPI-specification",
      "testing",
      "logs",
      "metrics",
      "traces",
      "intelligence-validation",
      "evidence-analysis",
      "verification-methods",
      "validation-techniques",
      "forensic-analysis",
      "audit-procedures",
      "unit-testing",
      "integration-testing",
      "test-driven-development",
      "pytest",
      "mocking",
      "test-coverage",
      "ci-cd"
    ],
    "specialtyInsights": [
      "Apply systemIntegration from integrationmaestro (97% expertise)",
      "Apply API Design Patterns from nexus-api (94% expertise)",
      "Apply Evidence Verification from hunter (93% expertise)",
      "Apply Testing & Quality Assurance from pythonista (93% expertise)",
      "Apply Testing & Quality Assurance from pythonista (93% expertise)"
    ],
    "confidenceScore": 0.829,
    "analysisDepth": "deep"
  }
}
