{
  "success": true,
  "response": {
    "content": "### 🧬 Multi-Personality Composed Response\n\n**Request**: Connect NEXUS to everything - APIs, webhooks, message queues, databases. Build middleware, ESB patterns, event streaming.\n\n**Composed Agent**: forge + guardian\n**Synergy Score**: 50%\n\n### 🎯 Trait Composition\n\n1. **Pipeline Architecture** (forge)\n   - Expertise: 94%\n   - Designs robust CI/CD pipelines with failure recovery and automated testing gates\n\n2. **Build System Integrity** (guardian)\n   - Expertise: 90%\n   - Ensures build configurations are consistent and optimized across environments\n\n### 💡 Integrated Analysis\n\nThis response leverages cognitive capabilities from **2 different personalities**, creating a ⚖️ **balanced** analytical framework.\n\n**Synergy Analysis**: 50.0% compatibility\n- 🔄 Moderate synergy - diverse perspectives with some coordination needed\n\n### 🔍 Multi-Perspective Insights\n\n**forge's Pipeline Architecture**\n- 📊 Expertise: 94% █████████░\n- 🎯 Specializes in: github-actions, docker, kubernetes, deployment-strategies\n- 🔔 Activates on: `deploy`, `pipeline`, `CI/CD`, `automation`, `build`\n- 💡 Designs robust CI/CD pipelines with failure recovery and automated testing gates\n\n**guardian's Build System Integrity**\n- 📊 Expertise: 90% █████████░\n- 🎯 Specializes in: build-pipelines, ci-cd, cross-platform, performance\n- 🔔 Activates on: `build`, `outDir`, `compilation`, `bundler`, `platform`\n- 💡 Ensures build configurations are consistent and optimized across environments\n\n### 📚 Combined Knowledge Domains (9)\n\ngithub-actions • docker • kubernetes • deployment-strategies • build-systems • build-pipelines • ci-cd • cross-platform • performance\n\n*This composed agent combines the best traits from 2 personalities for optimal task execution.*\n",
    "personalityUsed": "forge + guardian",
    "composedAgent": true,
    "nexusEnhanced": true,
    "traits": [
      {
        "name": "Pipeline Architecture",
        "personality": "forge",
        "expertise": 94
      },
      {
        "name": "Build System Integrity",
        "personality": "guardian",
        "expertise": 90
      }
    ],
    "traitApplications": [
      "Pipeline Architecture",
      "Build System Integrity"
    ],
    "synergyScore": 0.5,
    "knowledgeDomains": [
      "github-actions",
      "docker",
      "kubernetes",
      "deployment-strategies",
      "build-systems",
      "build-pipelines",
      "ci-cd",
      "cross-platform",
      "performance"
    ],
    "specialtyInsights": [
      "Apply Pipeline Architecture from forge (94% expertise)",
      "Apply Build System Integrity from guardian (90% expertise)"
    ],
    "confidenceScore": 0.7420000000000001,
    "analysisDepth": "moderate"
  }
}
