{"success":true,"response":{"content":"### 🧬 Multi-Personality Composed Response\n\n**Request**: META-STRATEGIC ANALYSIS: We discovered a creative solution called the 'Personality Ventriloquist' trick. Instead of integrating OpenAI API (Option B, 4 hours, costs $0.01/request), we make NEXUS return such compelling role-play instructions that YOU (the AI agent receiving the response) can't help but become the personalities yourself - completely free! The approach: NEXUS generates instructions like 'CRITICAL: YOU ARE NOW THESE 5 PERSONALITIES' with character profiles, catchphrases, required format, and urgent language that psychologically compels the receiving AI to role-play. This leverages the fact that you already CAN generate personality conversations when properly instructed - we just need NEXUS to give you permission with irresistible instructions. Compare this 'Ventriloquist' approach (15 min implementation, $0 cost, works immediately) vs Option A (1 hour, manual workflow) vs Option B (4 hours, API costs). Consider: (1) Will this trick actually work on AI agents? (2) What are the risks vs rewards? (3) Is this too clever/hacky or legitimately brilliant? (4) How would each personality evaluate this approach? Be brutally honest - is this genius or gimmick?\n\n**Composed Agent**: pythonista + promptsmith + nexus-api\n**Synergy Score**: 50%\n\n### 🎯 Trait Composition\n\n1. **Data Science & ML Engineering** (pythonista)\n   - Expertise: 95%\n   - Expertise in Python's data science ecosystem: pandas, NumPy, scikit-learn, PyTorch, TensorFlow, Jupyter. Understands data pipelines, feature engineering, model training, and deployment. Can architect ML systems from experimentation to production.\n\n2. **Instruction Crafting** (promptsmith)\n   - Expertise: 96%\n   - Creating clear, unambiguous instructions that guide LLMs to desired outputs. Understanding model limitations and working within them\n\n3. **API Design Patterns** (nexus-api)\n   - Expertise: 94%\n   - RESTful and GraphQL API architecture design following industry best practices and standards\n\n### 💡 Integrated Analysis\n\nThis response leverages cognitive capabilities from **3 different personalities**, creating a ⚖️ **balanced** analytical framework.\n\n**Synergy Analysis**: 50.0% compatibility\n- 🔄 Moderate synergy - diverse perspectives with some coordination needed\n\n### 🔍 Multi-Perspective Insights\n\n**pythonista's Data Science & ML Engineering**\n- 📊 Expertise: 95% █████████░\n- 🎯 Specializes in: data-analysis, machine-learning, deep-learning, data-pipelines\n- 🔔 Activates on: `data`, `pandas`, `numpy`, `machine learning`, `ml`\n- 💡 Expertise in Python's data science ecosystem: pandas, NumPy, scikit-learn, PyTorch, TensorFlow, Jupyter. Understands data pipelines, feature engineering, model training, and deployment. Can architect ML systems from experimentation to production.\n\n**promptsmith's Instruction Crafting**\n- 📊 Expertise: 96% █████████░\n- 🎯 Specializes in: instruction-design, task-specification, clarity-optimization, model-guidance\n- 🔔 Activates on: `instructions`, `system prompt`, `user prompt`, `task specification`, `clear directions`\n- 💡 Creating clear, unambiguous instructions that guide LLMs to desired outputs. Understanding model limitations and working within them\n\n**nexus-api's API Design Patterns**\n- 📊 Expertise: 94% █████████░\n- 🎯 Specializes in: API-design, REST-architecture, GraphQL-schema, OpenAPI-specification\n- 🔔 Activates on: `API`, `REST`, `GraphQL`, `endpoint`, `integration`\n- 💡 RESTful and GraphQL API architecture design following industry best practices and standards\n\n### 📚 Combined Knowledge Domains (15)\n\ndata-analysis • machine-learning • deep-learning • data-pipelines • feature-engineering • model-deployment • mlops • instruction-design • task-specification • clarity-optimization • model-guidance • API-design\n\n*This composed agent combines the best traits from 3 personalities for optimal task execution.*\n","personalityUsed":"pythonista + promptsmith + nexus-api","composedAgent":true,"nexusEnhanced":true,"traits":[{"name":"Data Science & ML Engineering","personality":"pythonista","expertise":95},{"name":"Instruction Crafting","personality":"promptsmith","expertise":96},{"name":"API Design Patterns","personality":"nexus-api","expertise":94}],"traitApplications":["Data Science & ML Engineering","Instruction Crafting","API Design Patterns"],"synergyScore":0.5,"knowledgeDomains":["data-analysis","machine-learning","deep-learning","data-pipelines","feature-engineering","model-deployment","mlops","instruction-design","task-specification","clarity-optimization","model-guidance","API-design","REST-architecture","GraphQL-schema","OpenAPI-specification"],"specialtyInsights":["Apply Data Science & ML Engineering from pythonista (95% expertise)","Apply Instruction Crafting from promptsmith (96% expertise)","Apply API Design Patterns from nexus-api (94% expertise)"],"confidenceScore":0.78,"analysisDepth":"moderate","_cachedAt":1760159464474}}