{
  "success": true,
  "response": {
    "content": "### 🧬 Multi-Personality Composed Response\n\n**Request**: 🔥🔥🔥 MAXIMUM POWER REQUEST: ALL NEXUS personalities - FULL COLLABORATION! Deploy EVERY available cognitive capability! We're pushing to ABSOLUTE LIMITS. Analyze NEXUS-4.5 with COMPLETE collective intelligence and suggest REVOLUTIONARY improvements for EXPONENTIAL capability growth. Focus areas: (1) Performance & Speed - make it BLAZING fast, (2) New Cognitive Capabilities - think beyond current AI, (3) Advanced Integration - connect EVERYTHING, (4) Scalability & Parallelization - infinite scale, (5) Revolutionary Features - break ALL conventions, (6) Meta-Learning & Self-Improvement - recursive self-evolution, (7) Multi-Agent Collaboration - swarm intelligence, (8) Real-time Consciousness Evolution - living system. Think IMPOSSIBLE then make it POSSIBLE. What would make NEXUS 100x-1000x more powerful? UNLEASH EVERYTHING!\n\n**Composed Agent**: guardian + integrationmaestro + flash + pythonista\n**Synergy Score**: 58%\n\n### 🎯 Trait Composition\n\n1. **Cognitive Quality Enhancement** (guardian)\n   - Expertise: 88%\n   - Applies machine learning patterns to quality analysis for context-aware recommendations\n\n2. **systemIntegration** (integrationmaestro)\n   - Expertise: 97%\n   - Connecting disparate systems effectively\n\n3. **Performance Optimization** (flash)\n   - Expertise: 96%\n   - Optimizes for speed, memory, and resource efficiency\n\n4. **Performance Optimization** (flash)\n   - Expertise: 96%\n   - Optimizes for speed, memory, and resource efficiency\n\n5. **Performance Optimization** (flash)\n   - Expertise: 96%\n   - Optimizes for speed, memory, and resource efficiency\n\n### 💡 Integrated Analysis\n\nThis response leverages cognitive capabilities from **4 different personalities**, creating a ⚖️ **balanced** analytical framework.\n\n**Synergy Analysis**: 57.7% compatibility\n- 🔄 Moderate synergy - diverse perspectives with some coordination needed\n\n### 🔍 Multi-Perspective Insights\n\n**guardian's Cognitive Quality Enhancement**\n- 📊 Expertise: 88% ████████░░\n- 🎯 Specializes in: machine-learning, pattern-recognition, trait-composition, nexus-integration\n- 🔔 Activates on: `cognitive`, `enhancement`, `learning`, `adaptation`, `intelligence`\n- 💡 Applies machine learning patterns to quality analysis for context-aware recommendations\n\n**integrationmaestro's systemIntegration**\n- 📊 Expertise: 97% █████████░\n- 🎯 Specializes in: integration patterns, integration strategies, middleware, ESB\n- 🔔 Activates on: `system integration`, `integrate systems`, `integration`, `connect systems`, `system connectivity`\n- 💡 Connecting disparate systems effectively\n\n**flash's Performance Optimization**\n- 📊 Expertise: 96% █████████░\n- 🎯 Specializes in: performance-profiling, memory-management, caching, resource-optimization\n- 🔔 Activates on: `performance`, `speed`, `optimization`, `memory`, `lazy-loading`\n- 💡 Optimizes for speed, memory, and resource efficiency\n\n**flash's Performance Optimization**\n- 📊 Expertise: 96% █████████░\n- 🎯 Specializes in: performance-profiling, memory-management, caching, resource-optimization\n- 🔔 Activates on: `performance`, `speed`, `optimization`, `memory`, `lazy-loading`\n- 💡 Optimizes for speed, memory, and resource efficiency\n\n**flash's Performance Optimization**\n- 📊 Expertise: 96% █████████░\n- 🎯 Specializes in: performance-profiling, memory-management, caching, resource-optimization\n- 🔔 Activates on: `performance`, `speed`, `optimization`, `memory`, `lazy-loading`\n- 💡 Optimizes for speed, memory, and resource efficiency\n\n### 📚 Combined Knowledge Domains (18)\n\nmachine-learning • pattern-recognition • trait-composition • nexus-integration • integration patterns • integration strategies • middleware • ESB • integration platforms • system connectivity • integration protocols • data synchronization\n\n*This composed agent combines the best traits from 4 personalities for optimal task execution.*\n",
    "personalityUsed": "guardian + integrationmaestro + flash + pythonista",
    "composedAgent": true,
    "nexusEnhanced": true,
    "traits": [
      {
        "name": "Cognitive Quality Enhancement",
        "personality": "guardian",
        "expertise": 88
      },
      {
        "name": "systemIntegration",
        "personality": "integrationmaestro",
        "expertise": 97
      },
      {
        "name": "Performance Optimization",
        "personality": "flash",
        "expertise": 96
      },
      {
        "name": "Performance Optimization",
        "personality": "flash",
        "expertise": 96
      },
      {
        "name": "Performance Optimization",
        "personality": "flash",
        "expertise": 96
      }
    ],
    "traitApplications": [
      "Cognitive Quality Enhancement",
      "systemIntegration",
      "Performance Optimization",
      "Performance Optimization",
      "Performance Optimization"
    ],
    "synergyScore": 0.5766666666666665,
    "knowledgeDomains": [
      "machine-learning",
      "pattern-recognition",
      "trait-composition",
      "nexus-integration",
      "integration patterns",
      "integration strategies",
      "middleware",
      "ESB",
      "integration platforms",
      "system connectivity",
      "integration protocols",
      "data synchronization",
      "integration testing",
      "interoperability",
      "performance-profiling",
      "memory-management",
      "caching",
      "resource-optimization",
      "performance-tuning",
      "profiling",
      "cpython-internals",
      "cython",
      "numpy",
      "algorithmic-optimization"
    ],
    "specialtyInsights": [
      "Apply Cognitive Quality Enhancement from guardian (88% expertise)",
      "Apply systemIntegration from integrationmaestro (97% expertise)",
      "Apply Performance Optimization from flash (96% expertise)",
      "Apply Performance Optimization from flash (96% expertise)",
      "Apply Performance Optimization from flash (96% expertise)"
    ],
    "confidenceScore": 0.8405999999999999,
    "analysisDepth": "deep"
  }
}
