{
  "success": true,
  "response": {
    "content": "### ğŸ§¬ Multi-Personality Composed Response\n\n**Request**: Analyze NEXUS-4.5 and suggest POWERFUL improvements to make it 10x-100x more capable. Focus on: Performance, Scalability, New Features, Integration, and Revolutionary Ideas. Be specific and actionable.\n\n**Composed Agent**: hunter\n**Synergy Score**: 100%\n\n### ğŸ¯ Trait Composition\n\n1. **Forensic Analysis** (hunter)\n   - Expertise: 95%\n   - Evidence-based verification of technical claims with brutal honesty about limitations\n\n### ğŸ’¡ Integrated Analysis\n\nThis response leverages cognitive capabilities from **1 different personalities**, creating a ğŸ”¥ **highly synergistic** analytical framework.\n\n**Synergy Analysis**: 100.0% compatibility\n- âœ¨ Exceptional team coherence - these personalities work seamlessly together\n\n### ğŸ” Multi-Perspective Insights\n\n**hunter's Forensic Analysis**\n- ğŸ“Š Expertise: 95% â–ˆâ–ˆâ–ˆâ–ˆâ–ˆâ–ˆâ–ˆâ–ˆâ–ˆâ–‘\n- ğŸ¯ Specializes in: testing, debugging, security, performance-analysis\n- ğŸ”” Activates on: `audit`, `verify`, `evidence`, `proof`, `gap`\n- ğŸ’¡ Evidence-based verification of technical claims with brutal honesty about limitations\n\n### ğŸ“š Combined Knowledge Domains (8)\n\ntesting â€¢ debugging â€¢ security â€¢ performance-analysis â€¢ root-cause-analysis â€¢ failure-analysis â€¢ incident-investigation â€¢ diagnostic-techniques\n\n*This composed agent combines the best traits from 1 personalities for optimal task execution.*\n",
    "personalityUsed": "hunter",
    "composedAgent": true,
    "nexusEnhanced": true,
    "traits": [
      {
        "name": "Forensic Analysis",
        "personality": "hunter",
        "expertise": 95
      }
    ],
    "traitApplications": [
      "Forensic Analysis"
    ],
    "synergyScore": 1,
    "knowledgeDomains": [
      "testing",
      "debugging",
      "security",
      "performance-analysis",
      "root-cause-analysis",
      "failure-analysis",
      "incident-investigation",
      "diagnostic-techniques"
    ],
    "specialtyInsights": [
      "Apply Forensic Analysis from hunter (95% expertise)",
      "High synergy detected: traits work exceptionally well together"
    ],
    "confidenceScore": 0.8899999999999999,
    "analysisDepth": "surface"
  }
}
