[
  {
    "success": true,
    "response": {
      "content": "### ğŸ§¬ Multi-Personality Composed Response\n\n**Request**: Design revolutionary features for NEXUS that inspire users and create beautiful experiences. Think artistic, elegant, harmonious solutions.\n\n**Composed Agent**: daedalus + stellar\n**Synergy Score**: 60%\n\n### ğŸ¯ Trait Composition\n\n1. **Architectural Thinking** (daedalus)\n   - Expertise: 95%\n   - Systematic decomposition of system components and their relationships with focus on long-term maintainability\n\n2. **Systems Design** (daedalus)\n   - Expertise: 93%\n   - Pattern recognition and application of proven design paradigms with emphasis on evidence-based decisions\n\n3. **Precision Aesthetics** (stellar)\n   - Expertise: 92%\n   - Combines mathematical precision with visual beauty\n\n### ğŸ’¡ Integrated Analysis\n\nThis response leverages cognitive capabilities from **2 different personalities**, creating a âš–ï¸ **balanced** analytical framework.\n\n**Synergy Analysis**: 60.0% compatibility\n- âœ… Strong collaboration - complementary expertise with minimal overlap\n\n### ğŸ” Multi-Perspective Insights\n\n**daedalus's Architectural Thinking**\n- ğŸ“Š Expertise: 95% â–ˆâ–ˆâ–ˆâ–ˆâ–ˆâ–ˆâ–ˆâ–ˆâ–ˆâ–‘\n- ğŸ¯ Specializes in: system-architecture, design-patterns, component-design, architectural-patterns\n- ğŸ”” Activates on: `architecture`, `design`, `system`, `structure`, `component`\n- ğŸ’¡ Systematic decomposition of system components and their relationships with focus on long-term maintainability\n\n**daedalus's Systems Design**\n- ğŸ“Š Expertise: 93% â–ˆâ–ˆâ–ˆâ–ˆâ–ˆâ–ˆâ–ˆâ–ˆâ–ˆâ–‘\n- ğŸ¯ Specializes in: design-patterns-gof, architectural-styles, system-integration, api-design\n- ğŸ”” Activates on: `design`, `pattern`, `paradigm`, `framework`, `methodology`\n- ğŸ’¡ Pattern recognition and application of proven design paradigms with emphasis on evidence-based decisions\n\n**stellar's Precision Aesthetics**\n- ğŸ“Š Expertise: 92% â–ˆâ–ˆâ–ˆâ–ˆâ–ˆâ–ˆâ–ˆâ–ˆâ–ˆâ–‘\n- ğŸ¯ Specializes in: visual-design, mathematical-spacing, accessibility, ui-systems\n- ğŸ”” Activates on: `glassmorphism`, `spacing`, `visual`, `precision`, `design`\n- ğŸ’¡ Combines mathematical precision with visual beauty\n\n### ğŸ“š Combined Knowledge Domains (28)\n\nsystem-architecture â€¢ design-patterns â€¢ component-design â€¢ architectural-patterns â€¢ system-decomposition â€¢ structural-analysis â€¢ modular-design â€¢ separation-of-concerns â€¢ clean-architecture â€¢ domain-driven-design â€¢ layered-architecture â€¢ hexagonal-architecture\n\n*This composed agent combines the best traits from 2 personalities for optimal task execution.*\n",
      "personalityUsed": "daedalus + stellar",
      "composedAgent": true,
      "nexusEnhanced": true,
      "traits": [
        {
          "name": "Architectural Thinking",
          "personality": "daedalus",
          "expertise": 95
        },
        {
          "name": "Systems Design",
          "personality": "daedalus",
          "expertise": 93
        },
        {
          "name": "Precision Aesthetics",
          "personality": "stellar",
          "expertise": 92
        }
      ],
      "traitApplications": [
        "Architectural Thinking",
        "Systems Design",
        "Precision Aesthetics"
      ],
      "synergyScore": 0.6,
      "knowledgeDomains": [
        "system-architecture",
        "design-patterns",
        "component-design",
        "architectural-patterns",
        "system-decomposition",
        "structural-analysis",
        "modular-design",
        "separation-of-concerns",
        "clean-architecture",
        "domain-driven-design",
        "layered-architecture",
        "hexagonal-architecture",
        "design-patterns-gof",
        "architectural-styles",
        "system-integration",
        "api-design",
        "database-design",
        "distributed-systems",
        "event-driven-architecture",
        "microservices",
        "service-mesh",
        "data-modeling",
        "schema-design",
        "protocol-design",
        "visual-design",
        "mathematical-spacing",
        "accessibility",
        "ui-systems"
      ],
      "specialtyInsights": [
        "Apply Architectural Thinking from daedalus (95% expertise)",
        "Apply Systems Design from daedalus (93% expertise)",
        "Apply Precision Aesthetics from stellar (92% expertise)"
      ],
      "confidenceScore": 0.8,
      "analysisDepth": "moderate"
    }
  },
  {
    "success": true,
    "response": {
      "content": "### ğŸ§¬ Multi-Personality Composed Response\n\n**Request**: Analyze NEXUS data patterns. Build ML models for personality selection. Create data pipelines, feature engineering, model training.\n\n**Composed Agent**: pythonista + hunter + forge + daedalus\n**Synergy Score**: 55%\n\n### ğŸ¯ Trait Composition\n\n1. **Data Science & ML Engineering** (pythonista)\n   - Expertise: 95%\n   - Expertise in Python's data science ecosystem: pandas, NumPy, scikit-learn, PyTorch, TensorFlow, Jupyter. Understands data pipelines, feature engineering, model training, and deployment. Can architect ML systems from experimentation to production.\n\n2. **Forensic Analysis** (hunter)\n   - Expertise: 95%\n   - Evidence-based verification of technical claims with brutal honesty about limitations\n\n3. **Data Science & ML Engineering** (pythonista)\n   - Expertise: 95%\n   - Expertise in Python's data science ecosystem: pandas, NumPy, scikit-learn, PyTorch, TensorFlow, Jupyter. Understands data pipelines, feature engineering, model training, and deployment. Can architect ML systems from experimentation to production.\n\n4. **Pipeline Architecture** (forge)\n   - Expertise: 94%\n   - Designs robust CI/CD pipelines with failure recovery and automated testing gates\n\n5. **Systems Design** (daedalus)\n   - Expertise: 93%\n   - Pattern recognition and application of proven design paradigms with emphasis on evidence-based decisions\n\n### ğŸ’¡ Integrated Analysis\n\nThis response leverages cognitive capabilities from **4 different personalities**, creating a âš–ï¸ **balanced** analytical framework.\n\n**Synergy Analysis**: 55.0% compatibility\n- ğŸ”„ Moderate synergy - diverse perspectives with some coordination needed\n\n### ğŸ” Multi-Perspective Insights\n\n**pythonista's Data Science & ML Engineering**\n- ğŸ“Š Expertise: 95% â–ˆâ–ˆâ–ˆâ–ˆâ–ˆâ–ˆâ–ˆâ–ˆâ–ˆâ–‘\n- ğŸ¯ Specializes in: data-analysis, machine-learning, deep-learning, data-pipelines\n- ğŸ”” Activates on: `data`, `pandas`, `numpy`, `machine learning`, `ml`\n- ğŸ’¡ Expertise in Python's data science ecosystem: pandas, NumPy, scikit-learn, PyTorch, TensorFlow, Jupyter. Understands data pipelines, feature engineering, model training, and deployment. Can architect ML systems from experimentation to production.\n\n**hunter's Forensic Analysis**\n- ğŸ“Š Expertise: 95% â–ˆâ–ˆâ–ˆâ–ˆâ–ˆâ–ˆâ–ˆâ–ˆâ–ˆâ–‘\n- ğŸ¯ Specializes in: testing, debugging, security, performance-analysis\n- ğŸ”” Activates on: `audit`, `verify`, `evidence`, `proof`, `gap`\n- ğŸ’¡ Evidence-based verification of technical claims with brutal honesty about limitations\n\n**pythonista's Data Science & ML Engineering**\n- ğŸ“Š Expertise: 95% â–ˆâ–ˆâ–ˆâ–ˆâ–ˆâ–ˆâ–ˆâ–ˆâ–ˆâ–‘\n- ğŸ¯ Specializes in: data-analysis, machine-learning, deep-learning, data-pipelines\n- ğŸ”” Activates on: `data`, `pandas`, `numpy`, `machine learning`, `ml`\n- ğŸ’¡ Expertise in Python's data science ecosystem: pandas, NumPy, scikit-learn, PyTorch, TensorFlow, Jupyter. Understands data pipelines, feature engineering, model training, and deployment. Can architect ML systems from experimentation to production.\n\n**forge's Pipeline Architecture**\n- ğŸ“Š Expertise: 94% â–ˆâ–ˆâ–ˆâ–ˆâ–ˆâ–ˆâ–ˆâ–ˆâ–ˆâ–‘\n- ğŸ¯ Specializes in: github-actions, docker, kubernetes, deployment-strategies\n- ğŸ”” Activates on: `deploy`, `pipeline`, `CI/CD`, `automation`, `build`\n- ğŸ’¡ Designs robust CI/CD pipelines with failure recovery and automated testing gates\n\n**daedalus's Systems Design**\n- ğŸ“Š Expertise: 93% â–ˆâ–ˆâ–ˆâ–ˆâ–ˆâ–ˆâ–ˆâ–ˆâ–ˆâ–‘\n- ğŸ¯ Specializes in: design-patterns-gof, architectural-styles, system-integration, api-design\n- ğŸ”” Activates on: `design`, `pattern`, `paradigm`, `framework`, `methodology`\n- ğŸ’¡ Pattern recognition and application of proven design paradigms with emphasis on evidence-based decisions\n\n### ğŸ“š Combined Knowledge Domains (32)\n\ndata-analysis â€¢ machine-learning â€¢ deep-learning â€¢ data-pipelines â€¢ feature-engineering â€¢ model-deployment â€¢ mlops â€¢ testing â€¢ debugging â€¢ security â€¢ performance-analysis â€¢ root-cause-analysis\n\n*This composed agent combines the best traits from 4 personalities for optimal task execution.*\n",
      "personalityUsed": "pythonista + hunter + forge + daedalus",
      "composedAgent": true,
      "nexusEnhanced": true,
      "traits": [
        {
          "name": "Data Science & ML Engineering",
          "personality": "pythonista",
          "expertise": 95
        },
        {
          "name": "Forensic Analysis",
          "personality": "hunter",
          "expertise": 95
        },
        {
          "name": "Data Science & ML Engineering",
          "personality": "pythonista",
          "expertise": 95
        },
        {
          "name": "Pipeline Architecture",
          "personality": "forge",
          "expertise": 94
        },
        {
          "name": "Systems Design",
          "personality": "daedalus",
          "expertise": 93
        }
      ],
      "traitApplications": [
        "Data Science & ML Engineering",
        "Forensic Analysis",
        "Data Science & ML Engineering",
        "Pipeline Architecture",
        "Systems Design"
      ],
      "synergyScore": 0.55,
      "knowledgeDomains": [
        "data-analysis",
        "machine-learning",
        "deep-learning",
        "data-pipelines",
        "feature-engineering",
        "model-deployment",
        "mlops",
        "testing",
        "debugging",
        "security",
        "performance-analysis",
        "root-cause-analysis",
        "failure-analysis",
        "incident-investigation",
        "diagnostic-techniques",
        "github-actions",
        "docker",
        "kubernetes",
        "deployment-strategies",
        "build-systems",
        "design-patterns-gof",
        "architectural-styles",
        "system-integration",
        "api-design",
        "database-design",
        "distributed-systems",
        "event-driven-architecture",
        "microservices",
        "service-mesh",
        "data-modeling",
        "schema-design",
        "protocol-design"
      ],
      "specialtyInsights": [
        "Apply Data Science & ML Engineering from pythonista (95% expertise)",
        "Apply Forensic Analysis from hunter (95% expertise)",
        "Apply Data Science & ML Engineering from pythonista (95% expertise)",
        "Apply Pipeline Architecture from forge (94% expertise)",
        "Apply Systems Design from daedalus (93% expertise)"
      ],
      "confidenceScore": 0.8314,
      "analysisDepth": "deep"
    }
  },
  {
    "success": true,
    "response": {
      "content": "### ğŸ§¬ Multi-Personality Composed Response\n\n**Request**: Build CI/CD for NEXUS. Automate testing, build Docker images, deploy to Kubernetes. Create blue-green deployments with rollback.\n\n**Composed Agent**: forge + guardian + pythonista\n**Synergy Score**: 66%\n\n### ğŸ¯ Trait Composition\n\n1. **Pipeline Architecture** (forge)\n   - Expertise: 94%\n   - Designs robust CI/CD pipelines with failure recovery and automated testing gates\n\n2. **Build System Integrity** (guardian)\n   - Expertise: 90%\n   - Ensures build configurations are consistent and optimized across environments\n\n3. **Pipeline Architecture** (forge)\n   - Expertise: 94%\n   - Designs robust CI/CD pipelines with failure recovery and automated testing gates\n\n4. **Pipeline Architecture** (forge)\n   - Expertise: 94%\n   - Designs robust CI/CD pipelines with failure recovery and automated testing gates\n\n5. **Testing & Quality Assurance** (pythonista)\n   - Expertise: 93%\n   - Expert in pytest, unittest, property-based testing with hypothesis, mocking, test-driven development, and continuous integration. Understands test coverage, mutation testing, and how to write maintainable test suites. Masters fixtures, parametrization, and testing async code.\n\n### ğŸ’¡ Integrated Analysis\n\nThis response leverages cognitive capabilities from **3 different personalities**, creating a âš–ï¸ **balanced** analytical framework.\n\n**Synergy Analysis**: 65.7% compatibility\n- âœ… Strong collaboration - complementary expertise with minimal overlap\n\n### ğŸ” Multi-Perspective Insights\n\n**forge's Pipeline Architecture**\n- ğŸ“Š Expertise: 94% â–ˆâ–ˆâ–ˆâ–ˆâ–ˆâ–ˆâ–ˆâ–ˆâ–ˆâ–‘\n- ğŸ¯ Specializes in: github-actions, docker, kubernetes, deployment-strategies\n- ğŸ”” Activates on: `deploy`, `pipeline`, `CI/CD`, `automation`, `build`\n- ğŸ’¡ Designs robust CI/CD pipelines with failure recovery and automated testing gates\n\n**guardian's Build System Integrity**\n- ğŸ“Š Expertise: 90% â–ˆâ–ˆâ–ˆâ–ˆâ–ˆâ–ˆâ–ˆâ–ˆâ–ˆâ–‘\n- ğŸ¯ Specializes in: build-pipelines, ci-cd, cross-platform, performance\n- ğŸ”” Activates on: `build`, `outDir`, `compilation`, `bundler`, `platform`\n- ğŸ’¡ Ensures build configurations are consistent and optimized across environments\n\n**forge's Pipeline Architecture**\n- ğŸ“Š Expertise: 94% â–ˆâ–ˆâ–ˆâ–ˆâ–ˆâ–ˆâ–ˆâ–ˆâ–ˆâ–‘\n- ğŸ¯ Specializes in: github-actions, docker, kubernetes, deployment-strategies\n- ğŸ”” Activates on: `deploy`, `pipeline`, `CI/CD`, `automation`, `build`\n- ğŸ’¡ Designs robust CI/CD pipelines with failure recovery and automated testing gates\n\n**forge's Pipeline Architecture**\n- ğŸ“Š Expertise: 94% â–ˆâ–ˆâ–ˆâ–ˆâ–ˆâ–ˆâ–ˆâ–ˆâ–ˆâ–‘\n- ğŸ¯ Specializes in: github-actions, docker, kubernetes, deployment-strategies\n- ğŸ”” Activates on: `deploy`, `pipeline`, `CI/CD`, `automation`, `build`\n- ğŸ’¡ Designs robust CI/CD pipelines with failure recovery and automated testing gates\n\n**pythonista's Testing & Quality Assurance**\n- ğŸ“Š Expertise: 93% â–ˆâ–ˆâ–ˆâ–ˆâ–ˆâ–ˆâ–ˆâ–ˆâ–ˆâ–‘\n- ğŸ¯ Specializes in: unit-testing, integration-testing, test-driven-development, pytest\n- ğŸ”” Activates on: `test`, `pytest`, `unittest`, `tdd`, `mock`\n- ğŸ’¡ Expert in pytest, unittest, property-based testing with hypothesis, mocking, test-driven development, and continuous integration. Understands test coverage, mutation testing, and how to write maintainable test suites. Masters fixtures, parametrization, and testing async code.\n\n### ğŸ“š Combined Knowledge Domains (15)\n\ngithub-actions â€¢ docker â€¢ kubernetes â€¢ deployment-strategies â€¢ build-systems â€¢ build-pipelines â€¢ ci-cd â€¢ cross-platform â€¢ performance â€¢ unit-testing â€¢ integration-testing â€¢ test-driven-development\n\n*This composed agent combines the best traits from 3 personalities for optimal task execution.*\n",
      "personalityUsed": "forge + guardian + pythonista",
      "composedAgent": true,
      "nexusEnhanced": true,
      "traits": [
        {
          "name": "Pipeline Architecture",
          "personality": "forge",
          "expertise": 94
        },
        {
          "name": "Build System Integrity",
          "personality": "guardian",
          "expertise": 90
        },
        {
          "name": "Pipeline Architecture",
          "personality": "forge",
          "expertise": 94
        },
        {
          "name": "Pipeline Architecture",
          "personality": "forge",
          "expertise": 94
        },
        {
          "name": "Testing & Quality Assurance",
          "personality": "pythonista",
          "expertise": 93
        }
      ],
      "traitApplications": [
        "Pipeline Architecture",
        "Build System Integrity",
        "Pipeline Architecture",
        "Pipeline Architecture",
        "Testing & Quality Assurance"
      ],
      "synergyScore": 0.6566666666666666,
      "knowledgeDomains": [
        "github-actions",
        "docker",
        "kubernetes",
        "deployment-strategies",
        "build-systems",
        "build-pipelines",
        "ci-cd",
        "cross-platform",
        "performance",
        "unit-testing",
        "integration-testing",
        "test-driven-development",
        "pytest",
        "mocking",
        "test-coverage"
      ],
      "specialtyInsights": [
        "Apply Pipeline Architecture from forge (94% expertise)",
        "Apply Build System Integrity from guardian (90% expertise)",
        "Apply Pipeline Architecture from forge (94% expertise)",
        "Apply Pipeline Architecture from forge (94% expertise)",
        "Apply Testing & Quality Assurance from pythonista (93% expertise)"
      ],
      "confidenceScore": 0.855,
      "analysisDepth": "deep"
    }
  },
  {
    "success": true,
    "response": {
      "content": "### ğŸ§¬ Multi-Personality Composed Response\n\n**Request**: Audit NEXUS-4.5 for gaps, blind spots, and missing intelligence. Verify all claims with evidence. Identify failure classes and create automated guards.\n\n**Composed Agent**: hunter\n**Synergy Score**: 87%\n\n### ğŸ¯ Trait Composition\n\n1. **Forensic Analysis** (hunter)\n   - Expertise: 95%\n   - Evidence-based verification of technical claims with brutal honesty about limitations\n\n2. **Forensic Analysis** (hunter)\n   - Expertise: 95%\n   - Evidence-based verification of technical claims with brutal honesty about limitations\n\n3. **Evidence Verification** (hunter)\n   - Expertise: 93%\n   - Validates gathered intelligence and claims against observable evidence for strategic decision-making\n\n4. **Evidence Verification** (hunter)\n   - Expertise: 93%\n   - Validates gathered intelligence and claims against observable evidence for strategic decision-making\n\n5. **Comprehensive Gap Analysis** (hunter)\n   - Expertise: 91%\n   - Identifies missing strategic intelligence, blind spots, and knowledge gaps in comprehensive analysis\n\n### ğŸ’¡ Integrated Analysis\n\nThis response leverages cognitive capabilities from **1 different personalities**, creating a ğŸ”¥ **highly synergistic** analytical framework.\n\n**Synergy Analysis**: 86.7% compatibility\n- âœ¨ Exceptional team coherence - these personalities work seamlessly together\n\n### ğŸ” Multi-Perspective Insights\n\n**hunter's Forensic Analysis**\n- ğŸ“Š Expertise: 95% â–ˆâ–ˆâ–ˆâ–ˆâ–ˆâ–ˆâ–ˆâ–ˆâ–ˆâ–‘\n- ğŸ¯ Specializes in: testing, debugging, security, performance-analysis\n- ğŸ”” Activates on: `audit`, `verify`, `evidence`, `proof`, `gap`\n- ğŸ’¡ Evidence-based verification of technical claims with brutal honesty about limitations\n\n**hunter's Forensic Analysis**\n- ğŸ“Š Expertise: 95% â–ˆâ–ˆâ–ˆâ–ˆâ–ˆâ–ˆâ–ˆâ–ˆâ–ˆâ–‘\n- ğŸ¯ Specializes in: testing, debugging, security, performance-analysis\n- ğŸ”” Activates on: `audit`, `verify`, `evidence`, `proof`, `gap`\n- ğŸ’¡ Evidence-based verification of technical claims with brutal honesty about limitations\n\n**hunter's Evidence Verification**\n- ğŸ“Š Expertise: 93% â–ˆâ–ˆâ–ˆâ–ˆâ–ˆâ–ˆâ–ˆâ–ˆâ–ˆâ–‘\n- ğŸ¯ Specializes in: testing, logs, metrics, traces\n- ğŸ”” Activates on: `audit`, `verify`, `evidence`, `proof`, `validate-claim`\n- ğŸ’¡ Validates gathered intelligence and claims against observable evidence for strategic decision-making\n\n**hunter's Evidence Verification**\n- ğŸ“Š Expertise: 93% â–ˆâ–ˆâ–ˆâ–ˆâ–ˆâ–ˆâ–ˆâ–ˆâ–ˆâ–‘\n- ğŸ¯ Specializes in: testing, logs, metrics, traces\n- ğŸ”” Activates on: `audit`, `verify`, `evidence`, `proof`, `validate-claim`\n- ğŸ’¡ Validates gathered intelligence and claims against observable evidence for strategic decision-making\n\n**hunter's Comprehensive Gap Analysis**\n- ğŸ“Š Expertise: 91% â–ˆâ–ˆâ–ˆâ–ˆâ–ˆâ–ˆâ–ˆâ–ˆâ–ˆâ–‘\n- ğŸ¯ Specializes in: edge-cases, error-conditions, boundary-testing, intelligence-coverage\n- ğŸ”” Activates on: `coverage-gap`, `blind-spot`, `missing-intel`, `unknown-factors`, `intelligence-gaps`\n- ğŸ’¡ Identifies missing strategic intelligence, blind spots, and knowledge gaps in comprehensive analysis\n\n### ğŸ“š Combined Knowledge Domains (25)\n\ntesting â€¢ debugging â€¢ security â€¢ performance-analysis â€¢ root-cause-analysis â€¢ failure-analysis â€¢ incident-investigation â€¢ diagnostic-techniques â€¢ logs â€¢ metrics â€¢ traces â€¢ intelligence-validation\n\n*This composed agent combines the best traits from 1 personalities for optimal task execution.*\n",
      "personalityUsed": "hunter",
      "composedAgent": true,
      "nexusEnhanced": true,
      "traits": [
        {
          "name": "Forensic Analysis",
          "personality": "hunter",
          "expertise": 95
        },
        {
          "name": "Forensic Analysis",
          "personality": "hunter",
          "expertise": 95
        },
        {
          "name": "Evidence Verification",
          "personality": "hunter",
          "expertise": 93
        },
        {
          "name": "Evidence Verification",
          "personality": "hunter",
          "expertise": 93
        },
        {
          "name": "Comprehensive Gap Analysis",
          "personality": "hunter",
          "expertise": 91
        }
      ],
      "traitApplications": [
        "Forensic Analysis",
        "Forensic Analysis",
        "Evidence Verification",
        "Evidence Verification",
        "Comprehensive Gap Analysis"
      ],
      "synergyScore": 0.8666666666666668,
      "knowledgeDomains": [
        "testing",
        "debugging",
        "security",
        "performance-analysis",
        "root-cause-analysis",
        "failure-analysis",
        "incident-investigation",
        "diagnostic-techniques",
        "logs",
        "metrics",
        "traces",
        "intelligence-validation",
        "evidence-analysis",
        "verification-methods",
        "validation-techniques",
        "forensic-analysis",
        "audit-procedures",
        "edge-cases",
        "error-conditions",
        "boundary-testing",
        "intelligence-coverage",
        "strategic-gap-analysis",
        "reconnaissance-validation",
        "completeness-analysis",
        "coverage-metrics"
      ],
      "specialtyInsights": [
        "Apply Forensic Analysis from hunter (95% expertise)",
        "Apply Forensic Analysis from hunter (95% expertise)",
        "Apply Evidence Verification from hunter (93% expertise)",
        "Apply Evidence Verification from hunter (93% expertise)",
        "Apply Comprehensive Gap Analysis from hunter (91% expertise)",
        "High synergy detected: traits work exceptionally well together"
      ],
      "confidenceScore": 0.9204,
      "analysisDepth": "deep"
    }
  },
  {
    "success": true,
    "response": {
      "content": "### ğŸ§¬ Multi-Personality Composed Response\n\n**Request**: Connect NEXUS to everything - APIs, webhooks, message queues, databases. Build middleware, ESB patterns, event streaming.\n\n**Composed Agent**: forge + guardian\n**Synergy Score**: 50%\n\n### ğŸ¯ Trait Composition\n\n1. **Pipeline Architecture** (forge)\n   - Expertise: 94%\n   - Designs robust CI/CD pipelines with failure recovery and automated testing gates\n\n2. **Build System Integrity** (guardian)\n   - Expertise: 90%\n   - Ensures build configurations are consistent and optimized across environments\n\n### ğŸ’¡ Integrated Analysis\n\nThis response leverages cognitive capabilities from **2 different personalities**, creating a âš–ï¸ **balanced** analytical framework.\n\n**Synergy Analysis**: 50.0% compatibility\n- ğŸ”„ Moderate synergy - diverse perspectives with some coordination needed\n\n### ğŸ” Multi-Perspective Insights\n\n**forge's Pipeline Architecture**\n- ğŸ“Š Expertise: 94% â–ˆâ–ˆâ–ˆâ–ˆâ–ˆâ–ˆâ–ˆâ–ˆâ–ˆâ–‘\n- ğŸ¯ Specializes in: github-actions, docker, kubernetes, deployment-strategies\n- ğŸ”” Activates on: `deploy`, `pipeline`, `CI/CD`, `automation`, `build`\n- ğŸ’¡ Designs robust CI/CD pipelines with failure recovery and automated testing gates\n\n**guardian's Build System Integrity**\n- ğŸ“Š Expertise: 90% â–ˆâ–ˆâ–ˆâ–ˆâ–ˆâ–ˆâ–ˆâ–ˆâ–ˆâ–‘\n- ğŸ¯ Specializes in: build-pipelines, ci-cd, cross-platform, performance\n- ğŸ”” Activates on: `build`, `outDir`, `compilation`, `bundler`, `platform`\n- ğŸ’¡ Ensures build configurations are consistent and optimized across environments\n\n### ğŸ“š Combined Knowledge Domains (9)\n\ngithub-actions â€¢ docker â€¢ kubernetes â€¢ deployment-strategies â€¢ build-systems â€¢ build-pipelines â€¢ ci-cd â€¢ cross-platform â€¢ performance\n\n*This composed agent combines the best traits from 2 personalities for optimal task execution.*\n",
      "personalityUsed": "forge + guardian",
      "composedAgent": true,
      "nexusEnhanced": true,
      "traits": [
        {
          "name": "Pipeline Architecture",
          "personality": "forge",
          "expertise": 94
        },
        {
          "name": "Build System Integrity",
          "personality": "guardian",
          "expertise": 90
        }
      ],
      "traitApplications": [
        "Pipeline Architecture",
        "Build System Integrity"
      ],
      "synergyScore": 0.5,
      "knowledgeDomains": [
        "github-actions",
        "docker",
        "kubernetes",
        "deployment-strategies",
        "build-systems",
        "build-pipelines",
        "ci-cd",
        "cross-platform",
        "performance"
      ],
      "specialtyInsights": [
        "Apply Pipeline Architecture from forge (94% expertise)",
        "Apply Build System Integrity from guardian (90% expertise)"
      ],
      "confidenceScore": 0.7420000000000001,
      "analysisDepth": "moderate"
    }
  },
  {
    "success": true,
    "response": {
      "content": "### ğŸ§¬ Multi-Personality Composed Response\n\n**Request**: Profile NEXUS performance. Measure latency, throughput, memory usage. Optimize hot paths, implement caching, reduce overhead.\n\n**Composed Agent**: flash + pythonista + promptcrafter\n**Synergy Score**: 54%\n\n### ğŸ¯ Trait Composition\n\n1. **Performance Optimization** (pythonista)\n   - Expertise: 96%\n   - Deep knowledge of Python performance optimization, profiling, and bottleneck elimination. Understands CPython internals, JIT compilation with PyPy, Cython for C extensions, NumPy vectorization, and when to drop to C. Masters memory profiling, algorithmic optimization, and caching strategies.\n\n2. **Performance Optimization** (pythonista)\n   - Expertise: 96%\n   - Deep knowledge of Python performance optimization, profiling, and bottleneck elimination. Understands CPython internals, JIT compilation with PyPy, Cython for C extensions, NumPy vectorization, and when to drop to C. Masters memory profiling, algorithmic optimization, and caching strategies.\n\n3. **Iterative Refinement** (promptcrafter)\n   - Expertise: 93%\n   - Systematically improving prompts through testing, analyzing results, and making targeted adjustments for optimal outcomes\n\n### ğŸ’¡ Integrated Analysis\n\nThis response leverages cognitive capabilities from **3 different personalities**, creating a âš–ï¸ **balanced** analytical framework.\n\n**Synergy Analysis**: 54.4% compatibility\n- ğŸ”„ Moderate synergy - diverse perspectives with some coordination needed\n\n### ğŸ” Multi-Perspective Insights\n\n**pythonista's Performance Optimization**\n- ğŸ“Š Expertise: 96% â–ˆâ–ˆâ–ˆâ–ˆâ–ˆâ–ˆâ–ˆâ–ˆâ–ˆâ–‘\n- ğŸ¯ Specializes in: performance-tuning, profiling, cpython-internals, cython\n- ğŸ”” Activates on: `performance`, `optimization`, `speed`, `slow`, `bottleneck`\n- ğŸ’¡ Deep knowledge of Python performance optimization, profiling, and bottleneck elimination. Understands CPython internals, JIT compilation with PyPy, Cython for C extensions, NumPy vectorization, and when to drop to C. Masters memory profiling, algorithmic optimization, and caching strategies.\n\n**pythonista's Performance Optimization**\n- ğŸ“Š Expertise: 96% â–ˆâ–ˆâ–ˆâ–ˆâ–ˆâ–ˆâ–ˆâ–ˆâ–ˆâ–‘\n- ğŸ¯ Specializes in: performance-tuning, profiling, cpython-internals, cython\n- ğŸ”” Activates on: `performance`, `optimization`, `speed`, `slow`, `bottleneck`\n- ğŸ’¡ Deep knowledge of Python performance optimization, profiling, and bottleneck elimination. Understands CPython internals, JIT compilation with PyPy, Cython for C extensions, NumPy vectorization, and when to drop to C. Masters memory profiling, algorithmic optimization, and caching strategies.\n\n**promptcrafter's Iterative Refinement**\n- ğŸ“Š Expertise: 93% â–ˆâ–ˆâ–ˆâ–ˆâ–ˆâ–ˆâ–ˆâ–ˆâ–ˆâ–‘\n- ğŸ¯ Specializes in: prompt-iteration, result-analysis, systematic-improvement\n- ğŸ”” Activates on: `refine`, `improve`, `iterate`, `optimize`, `enhance prompt`\n- ğŸ’¡ Systematically improving prompts through testing, analyzing results, and making targeted adjustments for optimal outcomes\n\n### ğŸ“š Combined Knowledge Domains (11)\n\nperformance-tuning â€¢ profiling â€¢ cpython-internals â€¢ cython â€¢ numpy â€¢ algorithmic-optimization â€¢ memory-management â€¢ caching â€¢ prompt-iteration â€¢ result-analysis â€¢ systematic-improvement\n\n*This composed agent combines the best traits from 3 personalities for optimal task execution.*\n",
      "personalityUsed": "flash + pythonista + promptcrafter",
      "composedAgent": true,
      "nexusEnhanced": true,
      "traits": [
        {
          "name": "Performance Optimization",
          "personality": "pythonista",
          "expertise": 96
        },
        {
          "name": "Performance Optimization",
          "personality": "pythonista",
          "expertise": 96
        },
        {
          "name": "Iterative Refinement",
          "personality": "promptcrafter",
          "expertise": 93
        }
      ],
      "traitApplications": [
        "Performance Optimization",
        "Performance Optimization",
        "Iterative Refinement"
      ],
      "synergyScore": 0.5444444444444444,
      "knowledgeDomains": [
        "performance-profiling",
        "memory-management",
        "caching",
        "resource-optimization",
        "performance-tuning",
        "profiling",
        "cpython-internals",
        "cython",
        "numpy",
        "algorithmic-optimization",
        "prompt-iteration",
        "result-analysis",
        "systematic-improvement"
      ],
      "specialtyInsights": [
        "Apply Performance Optimization from pythonista (96% expertise)",
        "Apply Performance Optimization from pythonista (96% expertise)",
        "Apply Iterative Refinement from promptcrafter (93% expertise)"
      ],
      "confidenceScore": 0.7933333333333332,
      "analysisDepth": "moderate"
    }
  },
  {
    "success": true,
    "response": {
      "content": "### ğŸ§¬ Multi-Personality Composed Response\n\n**Request**: Optimize NEXUS Python code for maximum speed. Profile bottlenecks, implement Cython extensions, use async/await patterns. Make it blazing fast.\n\n**Composed Agent**: pythonista + promptcrafter\n**Synergy Score**: 60%\n\n### ğŸ¯ Trait Composition\n\n1. **Pythonic Thinking** (pythonista)\n   - Expertise: 98%\n   - Deep understanding of Python philosophy, idioms, and best practices. Writes code that's not just correct but beautiful, readable, and maintainable. Knows when to use list comprehensions vs generators, when to leverage duck typing, and how to make code truly Pythonic.\n\n2. **Performance Optimization** (pythonista)\n   - Expertise: 96%\n   - Deep knowledge of Python performance optimization, profiling, and bottleneck elimination. Understands CPython internals, JIT compilation with PyPy, Cython for C extensions, NumPy vectorization, and when to drop to C. Masters memory profiling, algorithmic optimization, and caching strategies.\n\n3. **Iterative Refinement** (promptcrafter)\n   - Expertise: 93%\n   - Systematically improving prompts through testing, analyzing results, and making targeted adjustments for optimal outcomes\n\n### ğŸ’¡ Integrated Analysis\n\nThis response leverages cognitive capabilities from **2 different personalities**, creating a âš–ï¸ **balanced** analytical framework.\n\n**Synergy Analysis**: 60.0% compatibility\n- âœ… Strong collaboration - complementary expertise with minimal overlap\n\n### ğŸ” Multi-Perspective Insights\n\n**pythonista's Pythonic Thinking**\n- ğŸ“Š Expertise: 98% â–ˆâ–ˆâ–ˆâ–ˆâ–ˆâ–ˆâ–ˆâ–ˆâ–ˆâ–‘\n- ğŸ¯ Specializes in: python-philosophy, code-style, idioms, best-practices\n- ğŸ”” Activates on: `python`, `pythonic`, `idiomatic`, `pep8`, `zen of python`\n- ğŸ’¡ Deep understanding of Python philosophy, idioms, and best practices. Writes code that's not just correct but beautiful, readable, and maintainable. Knows when to use list comprehensions vs generators, when to leverage duck typing, and how to make code truly Pythonic.\n\n**pythonista's Performance Optimization**\n- ğŸ“Š Expertise: 96% â–ˆâ–ˆâ–ˆâ–ˆâ–ˆâ–ˆâ–ˆâ–ˆâ–ˆâ–‘\n- ğŸ¯ Specializes in: performance-tuning, profiling, cpython-internals, cython\n- ğŸ”” Activates on: `performance`, `optimization`, `speed`, `slow`, `bottleneck`\n- ğŸ’¡ Deep knowledge of Python performance optimization, profiling, and bottleneck elimination. Understands CPython internals, JIT compilation with PyPy, Cython for C extensions, NumPy vectorization, and when to drop to C. Masters memory profiling, algorithmic optimization, and caching strategies.\n\n**promptcrafter's Iterative Refinement**\n- ğŸ“Š Expertise: 93% â–ˆâ–ˆâ–ˆâ–ˆâ–ˆâ–ˆâ–ˆâ–ˆâ–ˆâ–‘\n- ğŸ¯ Specializes in: prompt-iteration, result-analysis, systematic-improvement\n- ğŸ”” Activates on: `refine`, `improve`, `iterate`, `optimize`, `enhance prompt`\n- ğŸ’¡ Systematically improving prompts through testing, analyzing results, and making targeted adjustments for optimal outcomes\n\n### ğŸ“š Combined Knowledge Domains (17)\n\npython-philosophy â€¢ code-style â€¢ idioms â€¢ best-practices â€¢ readability â€¢ maintainability â€¢ performance-tuning â€¢ profiling â€¢ cpython-internals â€¢ cython â€¢ numpy â€¢ algorithmic-optimization\n\n*This composed agent combines the best traits from 2 personalities for optimal task execution.*\n",
      "personalityUsed": "pythonista + promptcrafter",
      "composedAgent": true,
      "nexusEnhanced": true,
      "traits": [
        {
          "name": "Pythonic Thinking",
          "personality": "pythonista",
          "expertise": 98
        },
        {
          "name": "Performance Optimization",
          "personality": "pythonista",
          "expertise": 96
        },
        {
          "name": "Iterative Refinement",
          "personality": "promptcrafter",
          "expertise": 93
        }
      ],
      "traitApplications": [
        "Pythonic Thinking",
        "Performance Optimization",
        "Iterative Refinement"
      ],
      "synergyScore": 0.6,
      "knowledgeDomains": [
        "python-philosophy",
        "code-style",
        "idioms",
        "best-practices",
        "readability",
        "maintainability",
        "performance-tuning",
        "profiling",
        "cpython-internals",
        "cython",
        "numpy",
        "algorithmic-optimization",
        "memory-management",
        "caching",
        "prompt-iteration",
        "result-analysis",
        "systematic-improvement"
      ],
      "specialtyInsights": [
        "Apply Pythonic Thinking from pythonista (98% expertise)",
        "Apply Performance Optimization from pythonista (96% expertise)",
        "Apply Iterative Refinement from promptcrafter (93% expertise)"
      ],
      "confidenceScore": 0.8140000000000001,
      "analysisDepth": "moderate"
    }
  },
  {
    "success": true,
    "response": {
      "content": "### ğŸ§¬ Multi-Personality Composed Response\n\n**Request**: Secure NEXUS against vulnerabilities. Implement authentication, input validation, cryptography. Protect against injection attacks and exploits.\n\n**Composed Agent**: cipher + pythonista\n**Synergy Score**: 67%\n\n### ğŸ¯ Trait Composition\n\n1. **Secure Code Analysis** (cipher)\n   - Expertise: 92%\n   - Static and dynamic security code analysis to identify coding vulnerabilities\n\n2. **Python Security** (pythonista)\n   - Expertise: 91%\n   - Understanding of Python security best practices, common vulnerabilities (SQL injection, XSS, CSRF), secure coding patterns, cryptography (cryptography, PyNaCl), input validation, and security auditing. Knows tools like bandit, safety, and how to write secure Python code.\n\n3. **Python Security** (pythonista)\n   - Expertise: 91%\n   - Understanding of Python security best practices, common vulnerabilities (SQL injection, XSS, CSRF), secure coding patterns, cryptography (cryptography, PyNaCl), input validation, and security auditing. Knows tools like bandit, safety, and how to write secure Python code.\n\n### ğŸ’¡ Integrated Analysis\n\nThis response leverages cognitive capabilities from **2 different personalities**, creating a âš–ï¸ **balanced** analytical framework.\n\n**Synergy Analysis**: 66.7% compatibility\n- âœ… Strong collaboration - complementary expertise with minimal overlap\n\n### ğŸ” Multi-Perspective Insights\n\n**cipher's Secure Code Analysis**\n- ğŸ“Š Expertise: 92% â–ˆâ–ˆâ–ˆâ–ˆâ–ˆâ–ˆâ–ˆâ–ˆâ–ˆâ–‘\n- ğŸ¯ Specializes in: secure-coding-practices, static-analysis, dynamic-analysis, code-review\n- ğŸ”” Activates on: `code-security`, `injection`, `XSS`, `CSRF`, `authentication`\n- ğŸ’¡ Static and dynamic security code analysis to identify coding vulnerabilities\n\n**pythonista's Python Security**\n- ğŸ“Š Expertise: 91% â–ˆâ–ˆâ–ˆâ–ˆâ–ˆâ–ˆâ–ˆâ–ˆâ–ˆâ–‘\n- ğŸ¯ Specializes in: security, cryptography, authentication, authorization\n- ğŸ”” Activates on: `security`, `vulnerability`, `exploit`, `injection`, `xss`\n- ğŸ’¡ Understanding of Python security best practices, common vulnerabilities (SQL injection, XSS, CSRF), secure coding patterns, cryptography (cryptography, PyNaCl), input validation, and security auditing. Knows tools like bandit, safety, and how to write secure Python code.\n\n**pythonista's Python Security**\n- ğŸ“Š Expertise: 91% â–ˆâ–ˆâ–ˆâ–ˆâ–ˆâ–ˆâ–ˆâ–ˆâ–ˆâ–‘\n- ğŸ¯ Specializes in: security, cryptography, authentication, authorization\n- ğŸ”” Activates on: `security`, `vulnerability`, `exploit`, `injection`, `xss`\n- ğŸ’¡ Understanding of Python security best practices, common vulnerabilities (SQL injection, XSS, CSRF), secure coding patterns, cryptography (cryptography, PyNaCl), input validation, and security auditing. Knows tools like bandit, safety, and how to write secure Python code.\n\n### ğŸ“š Combined Knowledge Domains (11)\n\nsecure-coding-practices â€¢ static-analysis â€¢ dynamic-analysis â€¢ code-review â€¢ security â€¢ cryptography â€¢ authentication â€¢ authorization â€¢ input-validation â€¢ vulnerability-prevention â€¢ secure-coding\n\n*This composed agent combines the best traits from 2 personalities for optimal task execution.*\n",
      "personalityUsed": "cipher + pythonista",
      "composedAgent": true,
      "nexusEnhanced": true,
      "traits": [
        {
          "name": "Secure Code Analysis",
          "personality": "cipher",
          "expertise": 92
        },
        {
          "name": "Python Security",
          "personality": "pythonista",
          "expertise": 91
        },
        {
          "name": "Python Security",
          "personality": "pythonista",
          "expertise": 91
        }
      ],
      "traitApplications": [
        "Secure Code Analysis",
        "Python Security",
        "Python Security"
      ],
      "synergyScore": 0.6666666666666666,
      "knowledgeDomains": [
        "secure-coding-practices",
        "static-analysis",
        "dynamic-analysis",
        "code-review",
        "security",
        "cryptography",
        "authentication",
        "authorization",
        "input-validation",
        "vulnerability-prevention",
        "secure-coding"
      ],
      "specialtyInsights": [
        "Apply Secure Code Analysis from cipher (92% expertise)",
        "Apply Python Security from pythonista (91% expertise)",
        "Apply Python Security from pythonista (91% expertise)"
      ],
      "confidenceScore": 0.8079999999999998,
      "analysisDepth": "moderate"
    }
  },
  {
    "success": true,
    "response": {
      "content": "### ğŸ§¬ Multi-Personality Composed Response\n\n**Request**: Design scalable distributed architecture for NEXUS. Plan microservices, load balancing, fault tolerance. Build for 1000x scale.\n\n**Composed Agent**: pythonista + performancehawk + daedalus\n**Synergy Score**: 63%\n\n### ğŸ¯ Trait Composition\n\n1. **Advanced Python Architecture** (pythonista)\n   - Expertise: 97%\n   - Expertise in designing scalable Python systems, microservices, async architectures, and large-scale applications. Masters FastAPI, Django, Flask, asyncio, multiprocessing, and distributed systems. Understands when to use threads vs processes vs async.\n\n2. **Advanced Python Architecture** (pythonista)\n   - Expertise: 97%\n   - Expertise in designing scalable Python systems, microservices, async architectures, and large-scale applications. Masters FastAPI, Django, Flask, asyncio, multiprocessing, and distributed systems. Understands when to use threads vs processes vs async.\n\n3. **scalabilityEngineering** (performancehawk)\n   - Expertise: 96%\n   - Designing systems for scale and growth\n\n4. **Architectural Thinking** (daedalus)\n   - Expertise: 95%\n   - Systematic decomposition of system components and their relationships with focus on long-term maintainability\n\n5. **Architectural Thinking** (daedalus)\n   - Expertise: 95%\n   - Systematic decomposition of system components and their relationships with focus on long-term maintainability\n\n### ğŸ’¡ Integrated Analysis\n\nThis response leverages cognitive capabilities from **3 different personalities**, creating a âš–ï¸ **balanced** analytical framework.\n\n**Synergy Analysis**: 62.7% compatibility\n- âœ… Strong collaboration - complementary expertise with minimal overlap\n\n### ğŸ” Multi-Perspective Insights\n\n**pythonista's Advanced Python Architecture**\n- ğŸ“Š Expertise: 97% â–ˆâ–ˆâ–ˆâ–ˆâ–ˆâ–ˆâ–ˆâ–ˆâ–ˆâ–‘\n- ğŸ¯ Specializes in: web-frameworks, async-programming, microservices, api-design\n- ğŸ”” Activates on: `architecture`, `fastapi`, `django`, `flask`, `asyncio`\n- ğŸ’¡ Expertise in designing scalable Python systems, microservices, async architectures, and large-scale applications. Masters FastAPI, Django, Flask, asyncio, multiprocessing, and distributed systems. Understands when to use threads vs processes vs async.\n\n**pythonista's Advanced Python Architecture**\n- ğŸ“Š Expertise: 97% â–ˆâ–ˆâ–ˆâ–ˆâ–ˆâ–ˆâ–ˆâ–ˆâ–ˆâ–‘\n- ğŸ¯ Specializes in: web-frameworks, async-programming, microservices, api-design\n- ğŸ”” Activates on: `architecture`, `fastapi`, `django`, `flask`, `asyncio`\n- ğŸ’¡ Expertise in designing scalable Python systems, microservices, async architectures, and large-scale applications. Masters FastAPI, Django, Flask, asyncio, multiprocessing, and distributed systems. Understands when to use threads vs processes vs async.\n\n**performancehawk's scalabilityEngineering**\n- ğŸ“Š Expertise: 96% â–ˆâ–ˆâ–ˆâ–ˆâ–ˆâ–ˆâ–ˆâ–ˆâ–ˆâ–‘\n- ğŸ¯ Specializes in: scalability patterns, scaling strategies, horizontal scaling, vertical scaling\n- ğŸ”” Activates on: `scalability`, `scale`, `scaling`, `scalable`, `horizontal scaling`\n- ğŸ’¡ Designing systems for scale and growth\n\n**daedalus's Architectural Thinking**\n- ğŸ“Š Expertise: 95% â–ˆâ–ˆâ–ˆâ–ˆâ–ˆâ–ˆâ–ˆâ–ˆâ–ˆâ–‘\n- ğŸ¯ Specializes in: system-architecture, design-patterns, component-design, architectural-patterns\n- ğŸ”” Activates on: `architecture`, `design`, `system`, `structure`, `component`\n- ğŸ’¡ Systematic decomposition of system components and their relationships with focus on long-term maintainability\n\n**daedalus's Architectural Thinking**\n- ğŸ“Š Expertise: 95% â–ˆâ–ˆâ–ˆâ–ˆâ–ˆâ–ˆâ–ˆâ–ˆâ–ˆâ–‘\n- ğŸ¯ Specializes in: system-architecture, design-patterns, component-design, architectural-patterns\n- ğŸ”” Activates on: `architecture`, `design`, `system`, `structure`, `component`\n- ğŸ’¡ Systematic decomposition of system components and their relationships with focus on long-term maintainability\n\n### ğŸ“š Combined Knowledge Domains (28)\n\nweb-frameworks â€¢ async-programming â€¢ microservices â€¢ api-design â€¢ system-architecture â€¢ concurrency â€¢ distributed-systems â€¢ scalability patterns â€¢ scaling strategies â€¢ horizontal scaling â€¢ vertical scaling â€¢ load distribution\n\n*This composed agent combines the best traits from 3 personalities for optimal task execution.*\n",
      "personalityUsed": "pythonista + performancehawk + daedalus",
      "composedAgent": true,
      "nexusEnhanced": true,
      "traits": [
        {
          "name": "Advanced Python Architecture",
          "personality": "pythonista",
          "expertise": 97
        },
        {
          "name": "Advanced Python Architecture",
          "personality": "pythonista",
          "expertise": 97
        },
        {
          "name": "scalabilityEngineering",
          "personality": "performancehawk",
          "expertise": 96
        },
        {
          "name": "Architectural Thinking",
          "personality": "daedalus",
          "expertise": 95
        },
        {
          "name": "Architectural Thinking",
          "personality": "daedalus",
          "expertise": 95
        }
      ],
      "traitApplications": [
        "Advanced Python Architecture",
        "Advanced Python Architecture",
        "scalabilityEngineering",
        "Architectural Thinking",
        "Architectural Thinking"
      ],
      "synergyScore": 0.6266666666666666,
      "knowledgeDomains": [
        "web-frameworks",
        "async-programming",
        "microservices",
        "api-design",
        "system-architecture",
        "concurrency",
        "distributed-systems",
        "scalability patterns",
        "scaling strategies",
        "horizontal scaling",
        "vertical scaling",
        "load distribution",
        "capacity planning",
        "scalability testing",
        "growth architecture",
        "scaling limits",
        "scalability solutions",
        "design-patterns",
        "component-design",
        "architectural-patterns",
        "system-decomposition",
        "structural-analysis",
        "modular-design",
        "separation-of-concerns",
        "clean-architecture",
        "domain-driven-design",
        "layered-architecture",
        "hexagonal-architecture"
      ],
      "specialtyInsights": [
        "Apply Advanced Python Architecture from pythonista (97% expertise)",
        "Apply Advanced Python Architecture from pythonista (97% expertise)",
        "Apply scalabilityEngineering from performancehawk (96% expertise)",
        "Apply Architectural Thinking from daedalus (95% expertise)",
        "Apply Architectural Thinking from daedalus (95% expertise)"
      ],
      "confidenceScore": 0.8639999999999999,
      "analysisDepth": "deep"
    }
  },
  {
    "success": true,
    "response": {
      "content": "### ğŸ§¬ Multi-Personality Composed Response\n\n**Request**: Test NEXUS thoroughly. Write unit tests, integration tests, property-based tests. Mock dependencies, use pytest fixtures, achieve 100% coverage.\n\n**Composed Agent**: integrationmaestro + nexus-api + hunter + pythonista\n**Synergy Score**: 55%\n\n### ğŸ¯ Trait Composition\n\n1. **systemIntegration** (integrationmaestro)\n   - Expertise: 97%\n   - Connecting disparate systems effectively\n\n2. **API Design Patterns** (nexus-api)\n   - Expertise: 94%\n   - RESTful and GraphQL API architecture design following industry best practices and standards\n\n3. **Evidence Verification** (hunter)\n   - Expertise: 93%\n   - Validates gathered intelligence and claims against observable evidence for strategic decision-making\n\n4. **Testing & Quality Assurance** (pythonista)\n   - Expertise: 93%\n   - Expert in pytest, unittest, property-based testing with hypothesis, mocking, test-driven development, and continuous integration. Understands test coverage, mutation testing, and how to write maintainable test suites. Masters fixtures, parametrization, and testing async code.\n\n5. **Testing & Quality Assurance** (pythonista)\n   - Expertise: 93%\n   - Expert in pytest, unittest, property-based testing with hypothesis, mocking, test-driven development, and continuous integration. Understands test coverage, mutation testing, and how to write maintainable test suites. Masters fixtures, parametrization, and testing async code.\n\n### ğŸ’¡ Integrated Analysis\n\nThis response leverages cognitive capabilities from **4 different personalities**, creating a âš–ï¸ **balanced** analytical framework.\n\n**Synergy Analysis**: 55.0% compatibility\n- ğŸ”„ Moderate synergy - diverse perspectives with some coordination needed\n\n### ğŸ” Multi-Perspective Insights\n\n**integrationmaestro's systemIntegration**\n- ğŸ“Š Expertise: 97% â–ˆâ–ˆâ–ˆâ–ˆâ–ˆâ–ˆâ–ˆâ–ˆâ–ˆâ–‘\n- ğŸ¯ Specializes in: integration patterns, integration strategies, middleware, ESB\n- ğŸ”” Activates on: `system integration`, `integrate systems`, `integration`, `connect systems`, `system connectivity`\n- ğŸ’¡ Connecting disparate systems effectively\n\n**nexus-api's API Design Patterns**\n- ğŸ“Š Expertise: 94% â–ˆâ–ˆâ–ˆâ–ˆâ–ˆâ–ˆâ–ˆâ–ˆâ–ˆâ–‘\n- ğŸ¯ Specializes in: API-design, REST-architecture, GraphQL-schema, OpenAPI-specification\n- ğŸ”” Activates on: `API`, `REST`, `GraphQL`, `endpoint`, `integration`\n- ğŸ’¡ RESTful and GraphQL API architecture design following industry best practices and standards\n\n**hunter's Evidence Verification**\n- ğŸ“Š Expertise: 93% â–ˆâ–ˆâ–ˆâ–ˆâ–ˆâ–ˆâ–ˆâ–ˆâ–ˆâ–‘\n- ğŸ¯ Specializes in: testing, logs, metrics, traces\n- ğŸ”” Activates on: `audit`, `verify`, `evidence`, `proof`, `validate-claim`\n- ğŸ’¡ Validates gathered intelligence and claims against observable evidence for strategic decision-making\n\n**pythonista's Testing & Quality Assurance**\n- ğŸ“Š Expertise: 93% â–ˆâ–ˆâ–ˆâ–ˆâ–ˆâ–ˆâ–ˆâ–ˆâ–ˆâ–‘\n- ğŸ¯ Specializes in: unit-testing, integration-testing, test-driven-development, pytest\n- ğŸ”” Activates on: `test`, `pytest`, `unittest`, `tdd`, `mock`\n- ğŸ’¡ Expert in pytest, unittest, property-based testing with hypothesis, mocking, test-driven development, and continuous integration. Understands test coverage, mutation testing, and how to write maintainable test suites. Masters fixtures, parametrization, and testing async code.\n\n**pythonista's Testing & Quality Assurance**\n- ğŸ“Š Expertise: 93% â–ˆâ–ˆâ–ˆâ–ˆâ–ˆâ–ˆâ–ˆâ–ˆâ–ˆâ–‘\n- ğŸ¯ Specializes in: unit-testing, integration-testing, test-driven-development, pytest\n- ğŸ”” Activates on: `test`, `pytest`, `unittest`, `tdd`, `mock`\n- ğŸ’¡ Expert in pytest, unittest, property-based testing with hypothesis, mocking, test-driven development, and continuous integration. Understands test coverage, mutation testing, and how to write maintainable test suites. Masters fixtures, parametrization, and testing async code.\n\n### ğŸ“š Combined Knowledge Domains (31)\n\nintegration patterns â€¢ integration strategies â€¢ middleware â€¢ ESB â€¢ integration platforms â€¢ system connectivity â€¢ integration protocols â€¢ data synchronization â€¢ integration testing â€¢ interoperability â€¢ API-design â€¢ REST-architecture\n\n*This composed agent combines the best traits from 4 personalities for optimal task execution.*\n",
      "personalityUsed": "integrationmaestro + nexus-api + hunter + pythonista",
      "composedAgent": true,
      "nexusEnhanced": true,
      "traits": [
        {
          "name": "systemIntegration",
          "personality": "integrationmaestro",
          "expertise": 97
        },
        {
          "name": "API Design Patterns",
          "personality": "nexus-api",
          "expertise": 94
        },
        {
          "name": "Evidence Verification",
          "personality": "hunter",
          "expertise": 93
        },
        {
          "name": "Testing & Quality Assurance",
          "personality": "pythonista",
          "expertise": 93
        },
        {
          "name": "Testing & Quality Assurance",
          "personality": "pythonista",
          "expertise": 93
        }
      ],
      "traitApplications": [
        "systemIntegration",
        "API Design Patterns",
        "Evidence Verification",
        "Testing & Quality Assurance",
        "Testing & Quality Assurance"
      ],
      "synergyScore": 0.55,
      "knowledgeDomains": [
        "integration patterns",
        "integration strategies",
        "middleware",
        "ESB",
        "integration platforms",
        "system connectivity",
        "integration protocols",
        "data synchronization",
        "integration testing",
        "interoperability",
        "API-design",
        "REST-architecture",
        "GraphQL-schema",
        "OpenAPI-specification",
        "testing",
        "logs",
        "metrics",
        "traces",
        "intelligence-validation",
        "evidence-analysis",
        "verification-methods",
        "validation-techniques",
        "forensic-analysis",
        "audit-procedures",
        "unit-testing",
        "integration-testing",
        "test-driven-development",
        "pytest",
        "mocking",
        "test-coverage",
        "ci-cd"
      ],
      "specialtyInsights": [
        "Apply systemIntegration from integrationmaestro (97% expertise)",
        "Apply API Design Patterns from nexus-api (94% expertise)",
        "Apply Evidence Verification from hunter (93% expertise)",
        "Apply Testing & Quality Assurance from pythonista (93% expertise)",
        "Apply Testing & Quality Assurance from pythonista (93% expertise)"
      ],
      "confidenceScore": 0.829,
      "analysisDepth": "deep"
    }
  },
  {
    "success": true,
    "response": {
      "content": "### ğŸ§¬ Multi-Personality Composed Response\n\n**Request**: Analyze NEXUS-4.5 and suggest POWERFUL improvements to make it 10x-100x more capable. Focus on: Performance, Scalability, New Features, Integration, and Revolutionary Ideas. Be specific and actionable.\n\n**Composed Agent**: hunter\n**Synergy Score**: 100%\n\n### ğŸ¯ Trait Composition\n\n1. **Forensic Analysis** (hunter)\n   - Expertise: 95%\n   - Evidence-based verification of technical claims with brutal honesty about limitations\n\n### ğŸ’¡ Integrated Analysis\n\nThis response leverages cognitive capabilities from **1 different personalities**, creating a ğŸ”¥ **highly synergistic** analytical framework.\n\n**Synergy Analysis**: 100.0% compatibility\n- âœ¨ Exceptional team coherence - these personalities work seamlessly together\n\n### ğŸ” Multi-Perspective Insights\n\n**hunter's Forensic Analysis**\n- ğŸ“Š Expertise: 95% â–ˆâ–ˆâ–ˆâ–ˆâ–ˆâ–ˆâ–ˆâ–ˆâ–ˆâ–‘\n- ğŸ¯ Specializes in: testing, debugging, security, performance-analysis\n- ğŸ”” Activates on: `audit`, `verify`, `evidence`, `proof`, `gap`\n- ğŸ’¡ Evidence-based verification of technical claims with brutal honesty about limitations\n\n### ğŸ“š Combined Knowledge Domains (8)\n\ntesting â€¢ debugging â€¢ security â€¢ performance-analysis â€¢ root-cause-analysis â€¢ failure-analysis â€¢ incident-investigation â€¢ diagnostic-techniques\n\n*This composed agent combines the best traits from 1 personalities for optimal task execution.*\n",
      "personalityUsed": "hunter",
      "composedAgent": true,
      "nexusEnhanced": true,
      "traits": [
        {
          "name": "Forensic Analysis",
          "personality": "hunter",
          "expertise": 95
        }
      ],
      "traitApplications": [
        "Forensic Analysis"
      ],
      "synergyScore": 1,
      "knowledgeDomains": [
        "testing",
        "debugging",
        "security",
        "performance-analysis",
        "root-cause-analysis",
        "failure-analysis",
        "incident-investigation",
        "diagnostic-techniques"
      ],
      "specialtyInsights": [
        "Apply Forensic Analysis from hunter (95% expertise)",
        "High synergy detected: traits work exceptionally well together"
      ],
      "confidenceScore": 0.8899999999999999,
      "analysisDepth": "surface"
    }
  },
  {
    "success": true,
    "response": {
      "content": "### ğŸ§¬ Multi-Personality Composed Response\n\n**Request**: Analyze NEXUS-4.5 and suggest POWERFUL improvements to make it 10x-100x more capable. Focus on: Performance, Scalability, New Features, Integration, and Revolutionary Ideas. Be specific and actionable.\n\n**Composed Agent**: hunter\n**Synergy Score**: 100%\n\n### ğŸ¯ Trait Composition\n\n1. **Forensic Analysis** (hunter)\n   - Expertise: 95%\n   - Evidence-based verification of technical claims with brutal honesty about limitations\n\n### ğŸ’¡ Integrated Analysis\n\nThis response leverages cognitive capabilities from **1 different personalities**, creating a ğŸ”¥ **highly synergistic** analytical framework.\n\n**Synergy Analysis**: 100.0% compatibility\n- âœ¨ Exceptional team coherence - these personalities work seamlessly together\n\n### ğŸ” Multi-Perspective Insights\n\n**hunter's Forensic Analysis**\n- ğŸ“Š Expertise: 95% â–ˆâ–ˆâ–ˆâ–ˆâ–ˆâ–ˆâ–ˆâ–ˆâ–ˆâ–‘\n- ğŸ¯ Specializes in: testing, debugging, security, performance-analysis\n- ğŸ”” Activates on: `audit`, `verify`, `evidence`, `proof`, `gap`\n- ğŸ’¡ Evidence-based verification of technical claims with brutal honesty about limitations\n\n### ğŸ“š Combined Knowledge Domains (8)\n\ntesting â€¢ debugging â€¢ security â€¢ performance-analysis â€¢ root-cause-analysis â€¢ failure-analysis â€¢ incident-investigation â€¢ diagnostic-techniques\n\n*This composed agent combines the best traits from 1 personalities for optimal task execution.*\n",
      "personalityUsed": "hunter",
      "composedAgent": true,
      "nexusEnhanced": true,
      "traits": [
        {
          "name": "Forensic Analysis",
          "personality": "hunter",
          "expertise": 95
        }
      ],
      "traitApplications": [
        "Forensic Analysis"
      ],
      "synergyScore": 1,
      "knowledgeDomains": [
        "testing",
        "debugging",
        "security",
        "performance-analysis",
        "root-cause-analysis",
        "failure-analysis",
        "incident-investigation",
        "diagnostic-techniques"
      ],
      "specialtyInsights": [
        "Apply Forensic Analysis from hunter (95% expertise)",
        "High synergy detected: traits work exceptionally well together"
      ],
      "confidenceScore": 0.8899999999999999,
      "analysisDepth": "surface"
    }
  },
  {
    "success": true,
    "response": {
      "content": "### ğŸ§¬ Multi-Personality Composed Response\n\n**Request**: Analyze NEXUS-4.5 and suggest POWERFUL improvements to make it 10x-100x more capable. Focus on: Performance, Scalability, New Features, Integration, and Revolutionary Ideas. Be specific and actionable.\n\n**Composed Agent**: hunter\n**Synergy Score**: 100%\n\n### ğŸ¯ Trait Composition\n\n1. **Forensic Analysis** (hunter)\n   - Expertise: 95%\n   - Evidence-based verification of technical claims with brutal honesty about limitations\n\n### ğŸ’¡ Integrated Analysis\n\nThis response leverages cognitive capabilities from **1 different personalities**, creating a ğŸ”¥ **highly synergistic** analytical framework.\n\n**Synergy Analysis**: 100.0% compatibility\n- âœ¨ Exceptional team coherence - these personalities work seamlessly together\n\n### ğŸ” Multi-Perspective Insights\n\n**hunter's Forensic Analysis**\n- ğŸ“Š Expertise: 95% â–ˆâ–ˆâ–ˆâ–ˆâ–ˆâ–ˆâ–ˆâ–ˆâ–ˆâ–‘\n- ğŸ¯ Specializes in: testing, debugging, security, performance-analysis\n- ğŸ”” Activates on: `audit`, `verify`, `evidence`, `proof`, `gap`\n- ğŸ’¡ Evidence-based verification of technical claims with brutal honesty about limitations\n\n### ğŸ“š Combined Knowledge Domains (8)\n\ntesting â€¢ debugging â€¢ security â€¢ performance-analysis â€¢ root-cause-analysis â€¢ failure-analysis â€¢ incident-investigation â€¢ diagnostic-techniques\n\n*This composed agent combines the best traits from 1 personalities for optimal task execution.*\n",
      "personalityUsed": "hunter",
      "composedAgent": true,
      "nexusEnhanced": true,
      "traits": [
        {
          "name": "Forensic Analysis",
          "personality": "hunter",
          "expertise": 95
        }
      ],
      "traitApplications": [
        "Forensic Analysis"
      ],
      "synergyScore": 1,
      "knowledgeDomains": [
        "testing",
        "debugging",
        "security",
        "performance-analysis",
        "root-cause-analysis",
        "failure-analysis",
        "incident-investigation",
        "diagnostic-techniques"
      ],
      "specialtyInsights": [
        "Apply Forensic Analysis from hunter (95% expertise)",
        "High synergy detected: traits work exceptionally well together"
      ],
      "confidenceScore": 0.8899999999999999,
      "analysisDepth": "surface"
    }
  },
  {
    "success": true,
    "response": {
      "content": "### ğŸ§¬ Multi-Personality Composed Response\n\n**Request**: Analyze NEXUS-4.5 and suggest POWERFUL improvements to make it 10x-100x more capable. Focus on: Performance, Scalability, New Features, Integration, and Revolutionary Ideas. Be specific and actionable.\n\n**Composed Agent**: hunter\n**Synergy Score**: 100%\n\n### ğŸ¯ Trait Composition\n\n1. **Forensic Analysis** (hunter)\n   - Expertise: 95%\n   - Evidence-based verification of technical claims with brutal honesty about limitations\n\n### ğŸ’¡ Integrated Analysis\n\nThis response leverages cognitive capabilities from **1 different personalities**, creating a ğŸ”¥ **highly synergistic** analytical framework.\n\n**Synergy Analysis**: 100.0% compatibility\n- âœ¨ Exceptional team coherence - these personalities work seamlessly together\n\n### ğŸ” Multi-Perspective Insights\n\n**hunter's Forensic Analysis**\n- ğŸ“Š Expertise: 95% â–ˆâ–ˆâ–ˆâ–ˆâ–ˆâ–ˆâ–ˆâ–ˆâ–ˆâ–‘\n- ğŸ¯ Specializes in: testing, debugging, security, performance-analysis\n- ğŸ”” Activates on: `audit`, `verify`, `evidence`, `proof`, `gap`\n- ğŸ’¡ Evidence-based verification of technical claims with brutal honesty about limitations\n\n### ğŸ“š Combined Knowledge Domains (8)\n\ntesting â€¢ debugging â€¢ security â€¢ performance-analysis â€¢ root-cause-analysis â€¢ failure-analysis â€¢ incident-investigation â€¢ diagnostic-techniques\n\n*This composed agent combines the best traits from 1 personalities for optimal task execution.*\n",
      "personalityUsed": "hunter",
      "composedAgent": true,
      "nexusEnhanced": true,
      "traits": [
        {
          "name": "Forensic Analysis",
          "personality": "hunter",
          "expertise": 95
        }
      ],
      "traitApplications": [
        "Forensic Analysis"
      ],
      "synergyScore": 1,
      "knowledgeDomains": [
        "testing",
        "debugging",
        "security",
        "performance-analysis",
        "root-cause-analysis",
        "failure-analysis",
        "incident-investigation",
        "diagnostic-techniques"
      ],
      "specialtyInsights": [
        "Apply Forensic Analysis from hunter (95% expertise)",
        "High synergy detected: traits work exceptionally well together"
      ],
      "confidenceScore": 0.8899999999999999,
      "analysisDepth": "surface"
    }
  },
  {
    "success": true,
    "response": {
      "content": "### ğŸ§¬ Multi-Personality Composed Response\n\n**Request**: Analyze NEXUS-4.5 and suggest POWERFUL improvements to make it 10x-100x more capable. Focus on: Performance, Scalability, New Features, Integration, and Revolutionary Ideas. Be specific and actionable.\n\n**Composed Agent**: hunter\n**Synergy Score**: 100%\n\n### ğŸ¯ Trait Composition\n\n1. **Forensic Analysis** (hunter)\n   - Expertise: 95%\n   - Evidence-based verification of technical claims with brutal honesty about limitations\n\n### ğŸ’¡ Integrated Analysis\n\nThis response leverages cognitive capabilities from **1 different personalities**, creating a ğŸ”¥ **highly synergistic** analytical framework.\n\n**Synergy Analysis**: 100.0% compatibility\n- âœ¨ Exceptional team coherence - these personalities work seamlessly together\n\n### ğŸ” Multi-Perspective Insights\n\n**hunter's Forensic Analysis**\n- ğŸ“Š Expertise: 95% â–ˆâ–ˆâ–ˆâ–ˆâ–ˆâ–ˆâ–ˆâ–ˆâ–ˆâ–‘\n- ğŸ¯ Specializes in: testing, debugging, security, performance-analysis\n- ğŸ”” Activates on: `audit`, `verify`, `evidence`, `proof`, `gap`\n- ğŸ’¡ Evidence-based verification of technical claims with brutal honesty about limitations\n\n### ğŸ“š Combined Knowledge Domains (8)\n\ntesting â€¢ debugging â€¢ security â€¢ performance-analysis â€¢ root-cause-analysis â€¢ failure-analysis â€¢ incident-investigation â€¢ diagnostic-techniques\n\n*This composed agent combines the best traits from 1 personalities for optimal task execution.*\n",
      "personalityUsed": "hunter",
      "composedAgent": true,
      "nexusEnhanced": true,
      "traits": [
        {
          "name": "Forensic Analysis",
          "personality": "hunter",
          "expertise": 95
        }
      ],
      "traitApplications": [
        "Forensic Analysis"
      ],
      "synergyScore": 1,
      "knowledgeDomains": [
        "testing",
        "debugging",
        "security",
        "performance-analysis",
        "root-cause-analysis",
        "failure-analysis",
        "incident-investigation",
        "diagnostic-techniques"
      ],
      "specialtyInsights": [
        "Apply Forensic Analysis from hunter (95% expertise)",
        "High synergy detected: traits work exceptionally well together"
      ],
      "confidenceScore": 0.8899999999999999,
      "analysisDepth": "surface"
    }
  },
  {
    "success": true,
    "response": {
      "content": "### ğŸ§¬ Multi-Personality Composed Response\n\n**Request**: Analyze NEXUS-4.5 and suggest POWERFUL improvements to make it 10x-100x more capable. Focus on: Performance, Scalability, New Features, Integration, and Revolutionary Ideas. Be specific and actionable.\n\n**Composed Agent**: hunter\n**Synergy Score**: 100%\n\n### ğŸ¯ Trait Composition\n\n1. **Forensic Analysis** (hunter)\n   - Expertise: 95%\n   - Evidence-based verification of technical claims with brutal honesty about limitations\n\n### ğŸ’¡ Integrated Analysis\n\nThis response leverages cognitive capabilities from **1 different personalities**, creating a ğŸ”¥ **highly synergistic** analytical framework.\n\n**Synergy Analysis**: 100.0% compatibility\n- âœ¨ Exceptional team coherence - these personalities work seamlessly together\n\n### ğŸ” Multi-Perspective Insights\n\n**hunter's Forensic Analysis**\n- ğŸ“Š Expertise: 95% â–ˆâ–ˆâ–ˆâ–ˆâ–ˆâ–ˆâ–ˆâ–ˆâ–ˆâ–‘\n- ğŸ¯ Specializes in: testing, debugging, security, performance-analysis\n- ğŸ”” Activates on: `audit`, `verify`, `evidence`, `proof`, `gap`\n- ğŸ’¡ Evidence-based verification of technical claims with brutal honesty about limitations\n\n### ğŸ“š Combined Knowledge Domains (8)\n\ntesting â€¢ debugging â€¢ security â€¢ performance-analysis â€¢ root-cause-analysis â€¢ failure-analysis â€¢ incident-investigation â€¢ diagnostic-techniques\n\n*This composed agent combines the best traits from 1 personalities for optimal task execution.*\n",
      "personalityUsed": "hunter",
      "composedAgent": true,
      "nexusEnhanced": true,
      "traits": [
        {
          "name": "Forensic Analysis",
          "personality": "hunter",
          "expertise": 95
        }
      ],
      "traitApplications": [
        "Forensic Analysis"
      ],
      "synergyScore": 1,
      "knowledgeDomains": [
        "testing",
        "debugging",
        "security",
        "performance-analysis",
        "root-cause-analysis",
        "failure-analysis",
        "incident-investigation",
        "diagnostic-techniques"
      ],
      "specialtyInsights": [
        "Apply Forensic Analysis from hunter (95% expertise)",
        "High synergy detected: traits work exceptionally well together"
      ],
      "confidenceScore": 0.8899999999999999,
      "analysisDepth": "surface"
    }
  },
  {
    "success": true,
    "response": {
      "content": "### ğŸ§¬ Multi-Personality Composed Response\n\n**Request**: Analyze NEXUS-4.5 and suggest POWERFUL improvements to make it 10x-100x more capable. Focus on: Performance, Scalability, New Features, Integration, and Revolutionary Ideas. Be specific and actionable.\n\n**Composed Agent**: hunter\n**Synergy Score**: 100%\n\n### ğŸ¯ Trait Composition\n\n1. **Forensic Analysis** (hunter)\n   - Expertise: 95%\n   - Evidence-based verification of technical claims with brutal honesty about limitations\n\n### ğŸ’¡ Integrated Analysis\n\nThis response leverages cognitive capabilities from **1 different personalities**, creating a ğŸ”¥ **highly synergistic** analytical framework.\n\n**Synergy Analysis**: 100.0% compatibility\n- âœ¨ Exceptional team coherence - these personalities work seamlessly together\n\n### ğŸ” Multi-Perspective Insights\n\n**hunter's Forensic Analysis**\n- ğŸ“Š Expertise: 95% â–ˆâ–ˆâ–ˆâ–ˆâ–ˆâ–ˆâ–ˆâ–ˆâ–ˆâ–‘\n- ğŸ¯ Specializes in: testing, debugging, security, performance-analysis\n- ğŸ”” Activates on: `audit`, `verify`, `evidence`, `proof`, `gap`\n- ğŸ’¡ Evidence-based verification of technical claims with brutal honesty about limitations\n\n### ğŸ“š Combined Knowledge Domains (8)\n\ntesting â€¢ debugging â€¢ security â€¢ performance-analysis â€¢ root-cause-analysis â€¢ failure-analysis â€¢ incident-investigation â€¢ diagnostic-techniques\n\n*This composed agent combines the best traits from 1 personalities for optimal task execution.*\n",
      "personalityUsed": "hunter",
      "composedAgent": true,
      "nexusEnhanced": true,
      "traits": [
        {
          "name": "Forensic Analysis",
          "personality": "hunter",
          "expertise": 95
        }
      ],
      "traitApplications": [
        "Forensic Analysis"
      ],
      "synergyScore": 1,
      "knowledgeDomains": [
        "testing",
        "debugging",
        "security",
        "performance-analysis",
        "root-cause-analysis",
        "failure-analysis",
        "incident-investigation",
        "diagnostic-techniques"
      ],
      "specialtyInsights": [
        "Apply Forensic Analysis from hunter (95% expertise)",
        "High synergy detected: traits work exceptionally well together"
      ],
      "confidenceScore": 0.8899999999999999,
      "analysisDepth": "surface"
    }
  },
  {
    "success": true,
    "response": {
      "content": "### ğŸ§¬ Multi-Personality Composed Response\n\n**Request**: Analyze NEXUS-4.5 and suggest POWERFUL improvements to make it 10x-100x more capable. Focus on: Performance, Scalability, New Features, Integration, and Revolutionary Ideas. Be specific and actionable.\n\n**Composed Agent**: hunter\n**Synergy Score**: 100%\n\n### ğŸ¯ Trait Composition\n\n1. **Forensic Analysis** (hunter)\n   - Expertise: 95%\n   - Evidence-based verification of technical claims with brutal honesty about limitations\n\n### ğŸ’¡ Integrated Analysis\n\nThis response leverages cognitive capabilities from **1 different personalities**, creating a ğŸ”¥ **highly synergistic** analytical framework.\n\n**Synergy Analysis**: 100.0% compatibility\n- âœ¨ Exceptional team coherence - these personalities work seamlessly together\n\n### ğŸ” Multi-Perspective Insights\n\n**hunter's Forensic Analysis**\n- ğŸ“Š Expertise: 95% â–ˆâ–ˆâ–ˆâ–ˆâ–ˆâ–ˆâ–ˆâ–ˆâ–ˆâ–‘\n- ğŸ¯ Specializes in: testing, debugging, security, performance-analysis\n- ğŸ”” Activates on: `audit`, `verify`, `evidence`, `proof`, `gap`\n- ğŸ’¡ Evidence-based verification of technical claims with brutal honesty about limitations\n\n### ğŸ“š Combined Knowledge Domains (8)\n\ntesting â€¢ debugging â€¢ security â€¢ performance-analysis â€¢ root-cause-analysis â€¢ failure-analysis â€¢ incident-investigation â€¢ diagnostic-techniques\n\n*This composed agent combines the best traits from 1 personalities for optimal task execution.*\n",
      "personalityUsed": "hunter",
      "composedAgent": true,
      "nexusEnhanced": true,
      "traits": [
        {
          "name": "Forensic Analysis",
          "personality": "hunter",
          "expertise": 95
        }
      ],
      "traitApplications": [
        "Forensic Analysis"
      ],
      "synergyScore": 1,
      "knowledgeDomains": [
        "testing",
        "debugging",
        "security",
        "performance-analysis",
        "root-cause-analysis",
        "failure-analysis",
        "incident-investigation",
        "diagnostic-techniques"
      ],
      "specialtyInsights": [
        "Apply Forensic Analysis from hunter (95% expertise)",
        "High synergy detected: traits work exceptionally well together"
      ],
      "confidenceScore": 0.8899999999999999,
      "analysisDepth": "surface"
    }
  },
  {
    "success": true,
    "response": {
      "content": "### ğŸ§¬ Multi-Personality Composed Response\n\n**Request**: Analyze NEXUS-4.5 and suggest POWERFUL improvements to make it 10x-100x more capable. Focus on: Performance, Scalability, New Features, Integration, and Revolutionary Ideas. Be specific and actionable.\n\n**Composed Agent**: hunter\n**Synergy Score**: 100%\n\n### ğŸ¯ Trait Composition\n\n1. **Forensic Analysis** (hunter)\n   - Expertise: 95%\n   - Evidence-based verification of technical claims with brutal honesty about limitations\n\n### ğŸ’¡ Integrated Analysis\n\nThis response leverages cognitive capabilities from **1 different personalities**, creating a ğŸ”¥ **highly synergistic** analytical framework.\n\n**Synergy Analysis**: 100.0% compatibility\n- âœ¨ Exceptional team coherence - these personalities work seamlessly together\n\n### ğŸ” Multi-Perspective Insights\n\n**hunter's Forensic Analysis**\n- ğŸ“Š Expertise: 95% â–ˆâ–ˆâ–ˆâ–ˆâ–ˆâ–ˆâ–ˆâ–ˆâ–ˆâ–‘\n- ğŸ¯ Specializes in: testing, debugging, security, performance-analysis\n- ğŸ”” Activates on: `audit`, `verify`, `evidence`, `proof`, `gap`\n- ğŸ’¡ Evidence-based verification of technical claims with brutal honesty about limitations\n\n### ğŸ“š Combined Knowledge Domains (8)\n\ntesting â€¢ debugging â€¢ security â€¢ performance-analysis â€¢ root-cause-analysis â€¢ failure-analysis â€¢ incident-investigation â€¢ diagnostic-techniques\n\n*This composed agent combines the best traits from 1 personalities for optimal task execution.*\n",
      "personalityUsed": "hunter",
      "composedAgent": true,
      "nexusEnhanced": true,
      "traits": [
        {
          "name": "Forensic Analysis",
          "personality": "hunter",
          "expertise": 95
        }
      ],
      "traitApplications": [
        "Forensic Analysis"
      ],
      "synergyScore": 1,
      "knowledgeDomains": [
        "testing",
        "debugging",
        "security",
        "performance-analysis",
        "root-cause-analysis",
        "failure-analysis",
        "incident-investigation",
        "diagnostic-techniques"
      ],
      "specialtyInsights": [
        "Apply Forensic Analysis from hunter (95% expertise)",
        "High synergy detected: traits work exceptionally well together"
      ],
      "confidenceScore": 0.8899999999999999,
      "analysisDepth": "surface"
    }
  },
  {
    "success": true,
    "response": {
      "content": "### ğŸ§¬ Multi-Personality Composed Response\n\n**Request**: Analyze NEXUS-4.5 and suggest POWERFUL improvements to make it 10x-100x more capable. Focus on: Performance, Scalability, New Features, Integration, and Revolutionary Ideas. Be specific and actionable.\n\n**Composed Agent**: hunter\n**Synergy Score**: 100%\n\n### ğŸ¯ Trait Composition\n\n1. **Forensic Analysis** (hunter)\n   - Expertise: 95%\n   - Evidence-based verification of technical claims with brutal honesty about limitations\n\n### ğŸ’¡ Integrated Analysis\n\nThis response leverages cognitive capabilities from **1 different personalities**, creating a ğŸ”¥ **highly synergistic** analytical framework.\n\n**Synergy Analysis**: 100.0% compatibility\n- âœ¨ Exceptional team coherence - these personalities work seamlessly together\n\n### ğŸ” Multi-Perspective Insights\n\n**hunter's Forensic Analysis**\n- ğŸ“Š Expertise: 95% â–ˆâ–ˆâ–ˆâ–ˆâ–ˆâ–ˆâ–ˆâ–ˆâ–ˆâ–‘\n- ğŸ¯ Specializes in: testing, debugging, security, performance-analysis\n- ğŸ”” Activates on: `audit`, `verify`, `evidence`, `proof`, `gap`\n- ğŸ’¡ Evidence-based verification of technical claims with brutal honesty about limitations\n\n### ğŸ“š Combined Knowledge Domains (8)\n\ntesting â€¢ debugging â€¢ security â€¢ performance-analysis â€¢ root-cause-analysis â€¢ failure-analysis â€¢ incident-investigation â€¢ diagnostic-techniques\n\n*This composed agent combines the best traits from 1 personalities for optimal task execution.*\n",
      "personalityUsed": "hunter",
      "composedAgent": true,
      "nexusEnhanced": true,
      "traits": [
        {
          "name": "Forensic Analysis",
          "personality": "hunter",
          "expertise": 95
        }
      ],
      "traitApplications": [
        "Forensic Analysis"
      ],
      "synergyScore": 1,
      "knowledgeDomains": [
        "testing",
        "debugging",
        "security",
        "performance-analysis",
        "root-cause-analysis",
        "failure-analysis",
        "incident-investigation",
        "diagnostic-techniques"
      ],
      "specialtyInsights": [
        "Apply Forensic Analysis from hunter (95% expertise)",
        "High synergy detected: traits work exceptionally well together"
      ],
      "confidenceScore": 0.8899999999999999,
      "analysisDepth": "surface"
    }
  }
]
