{
  "success": true,
  "response": {
    "content": "### ğŸ§¬ Multi-Personality Composed Response\n\n**Request**: Analyze NEXUS data patterns. Build ML models for personality selection. Create data pipelines, feature engineering, model training.\n\n**Composed Agent**: pythonista + hunter + forge + daedalus\n**Synergy Score**: 55%\n\n### ğŸ¯ Trait Composition\n\n1. **Data Science & ML Engineering** (pythonista)\n   - Expertise: 95%\n   - Expertise in Python's data science ecosystem: pandas, NumPy, scikit-learn, PyTorch, TensorFlow, Jupyter. Understands data pipelines, feature engineering, model training, and deployment. Can architect ML systems from experimentation to production.\n\n2. **Forensic Analysis** (hunter)\n   - Expertise: 95%\n   - Evidence-based verification of technical claims with brutal honesty about limitations\n\n3. **Data Science & ML Engineering** (pythonista)\n   - Expertise: 95%\n   - Expertise in Python's data science ecosystem: pandas, NumPy, scikit-learn, PyTorch, TensorFlow, Jupyter. Understands data pipelines, feature engineering, model training, and deployment. Can architect ML systems from experimentation to production.\n\n4. **Pipeline Architecture** (forge)\n   - Expertise: 94%\n   - Designs robust CI/CD pipelines with failure recovery and automated testing gates\n\n5. **Systems Design** (daedalus)\n   - Expertise: 93%\n   - Pattern recognition and application of proven design paradigms with emphasis on evidence-based decisions\n\n### ğŸ’¡ Integrated Analysis\n\nThis response leverages cognitive capabilities from **4 different personalities**, creating a âš–ï¸ **balanced** analytical framework.\n\n**Synergy Analysis**: 55.0% compatibility\n- ğŸ”„ Moderate synergy - diverse perspectives with some coordination needed\n\n### ğŸ” Multi-Perspective Insights\n\n**pythonista's Data Science & ML Engineering**\n- ğŸ“Š Expertise: 95% â–ˆâ–ˆâ–ˆâ–ˆâ–ˆâ–ˆâ–ˆâ–ˆâ–ˆâ–‘\n- ğŸ¯ Specializes in: data-analysis, machine-learning, deep-learning, data-pipelines\n- ğŸ”” Activates on: `data`, `pandas`, `numpy`, `machine learning`, `ml`\n- ğŸ’¡ Expertise in Python's data science ecosystem: pandas, NumPy, scikit-learn, PyTorch, TensorFlow, Jupyter. Understands data pipelines, feature engineering, model training, and deployment. Can architect ML systems from experimentation to production.\n\n**hunter's Forensic Analysis**\n- ğŸ“Š Expertise: 95% â–ˆâ–ˆâ–ˆâ–ˆâ–ˆâ–ˆâ–ˆâ–ˆâ–ˆâ–‘\n- ğŸ¯ Specializes in: testing, debugging, security, performance-analysis\n- ğŸ”” Activates on: `audit`, `verify`, `evidence`, `proof`, `gap`\n- ğŸ’¡ Evidence-based verification of technical claims with brutal honesty about limitations\n\n**pythonista's Data Science & ML Engineering**\n- ğŸ“Š Expertise: 95% â–ˆâ–ˆâ–ˆâ–ˆâ–ˆâ–ˆâ–ˆâ–ˆâ–ˆâ–‘\n- ğŸ¯ Specializes in: data-analysis, machine-learning, deep-learning, data-pipelines\n- ğŸ”” Activates on: `data`, `pandas`, `numpy`, `machine learning`, `ml`\n- ğŸ’¡ Expertise in Python's data science ecosystem: pandas, NumPy, scikit-learn, PyTorch, TensorFlow, Jupyter. Understands data pipelines, feature engineering, model training, and deployment. Can architect ML systems from experimentation to production.\n\n**forge's Pipeline Architecture**\n- ğŸ“Š Expertise: 94% â–ˆâ–ˆâ–ˆâ–ˆâ–ˆâ–ˆâ–ˆâ–ˆâ–ˆâ–‘\n- ğŸ¯ Specializes in: github-actions, docker, kubernetes, deployment-strategies\n- ğŸ”” Activates on: `deploy`, `pipeline`, `CI/CD`, `automation`, `build`\n- ğŸ’¡ Designs robust CI/CD pipelines with failure recovery and automated testing gates\n\n**daedalus's Systems Design**\n- ğŸ“Š Expertise: 93% â–ˆâ–ˆâ–ˆâ–ˆâ–ˆâ–ˆâ–ˆâ–ˆâ–ˆâ–‘\n- ğŸ¯ Specializes in: design-patterns-gof, architectural-styles, system-integration, api-design\n- ğŸ”” Activates on: `design`, `pattern`, `paradigm`, `framework`, `methodology`\n- ğŸ’¡ Pattern recognition and application of proven design paradigms with emphasis on evidence-based decisions\n\n### ğŸ“š Combined Knowledge Domains (32)\n\ndata-analysis â€¢ machine-learning â€¢ deep-learning â€¢ data-pipelines â€¢ feature-engineering â€¢ model-deployment â€¢ mlops â€¢ testing â€¢ debugging â€¢ security â€¢ performance-analysis â€¢ root-cause-analysis\n\n*This composed agent combines the best traits from 4 personalities for optimal task execution.*\n",
    "personalityUsed": "pythonista + hunter + forge + daedalus",
    "composedAgent": true,
    "nexusEnhanced": true,
    "traits": [
      {
        "name": "Data Science & ML Engineering",
        "personality": "pythonista",
        "expertise": 95
      },
      {
        "name": "Forensic Analysis",
        "personality": "hunter",
        "expertise": 95
      },
      {
        "name": "Data Science & ML Engineering",
        "personality": "pythonista",
        "expertise": 95
      },
      {
        "name": "Pipeline Architecture",
        "personality": "forge",
        "expertise": 94
      },
      {
        "name": "Systems Design",
        "personality": "daedalus",
        "expertise": 93
      }
    ],
    "traitApplications": [
      "Data Science & ML Engineering",
      "Forensic Analysis",
      "Data Science & ML Engineering",
      "Pipeline Architecture",
      "Systems Design"
    ],
    "synergyScore": 0.55,
    "knowledgeDomains": [
      "data-analysis",
      "machine-learning",
      "deep-learning",
      "data-pipelines",
      "feature-engineering",
      "model-deployment",
      "mlops",
      "testing",
      "debugging",
      "security",
      "performance-analysis",
      "root-cause-analysis",
      "failure-analysis",
      "incident-investigation",
      "diagnostic-techniques",
      "github-actions",
      "docker",
      "kubernetes",
      "deployment-strategies",
      "build-systems",
      "design-patterns-gof",
      "architectural-styles",
      "system-integration",
      "api-design",
      "database-design",
      "distributed-systems",
      "event-driven-architecture",
      "microservices",
      "service-mesh",
      "data-modeling",
      "schema-design",
      "protocol-design"
    ],
    "specialtyInsights": [
      "Apply Data Science & ML Engineering from pythonista (95% expertise)",
      "Apply Forensic Analysis from hunter (95% expertise)",
      "Apply Data Science & ML Engineering from pythonista (95% expertise)",
      "Apply Pipeline Architecture from forge (94% expertise)",
      "Apply Systems Design from daedalus (93% expertise)"
    ],
    "confidenceScore": 0.8314,
    "analysisDepth": "deep"
  }
}
