{
  "success": true,
  "response": {
    "content": "### 🧬 Multi-Personality Composed Response\n\n**Request**: Design revolutionary features for NEXUS that inspire users and create beautiful experiences. Think artistic, elegant, harmonious solutions.\n\n**Composed Agent**: daedalus + stellar\n**Synergy Score**: 60%\n\n### 🎯 Trait Composition\n\n1. **Architectural Thinking** (daedalus)\n   - Expertise: 95%\n   - Systematic decomposition of system components and their relationships with focus on long-term maintainability\n\n2. **Systems Design** (daedalus)\n   - Expertise: 93%\n   - Pattern recognition and application of proven design paradigms with emphasis on evidence-based decisions\n\n3. **Precision Aesthetics** (stellar)\n   - Expertise: 92%\n   - Combines mathematical precision with visual beauty\n\n### 💡 Integrated Analysis\n\nThis response leverages cognitive capabilities from **2 different personalities**, creating a ⚖️ **balanced** analytical framework.\n\n**Synergy Analysis**: 60.0% compatibility\n- ✅ Strong collaboration - complementary expertise with minimal overlap\n\n### 🔍 Multi-Perspective Insights\n\n**daedalus's Architectural Thinking**\n- 📊 Expertise: 95% █████████░\n- 🎯 Specializes in: system-architecture, design-patterns, component-design, architectural-patterns\n- 🔔 Activates on: `architecture`, `design`, `system`, `structure`, `component`\n- 💡 Systematic decomposition of system components and their relationships with focus on long-term maintainability\n\n**daedalus's Systems Design**\n- 📊 Expertise: 93% █████████░\n- 🎯 Specializes in: design-patterns-gof, architectural-styles, system-integration, api-design\n- 🔔 Activates on: `design`, `pattern`, `paradigm`, `framework`, `methodology`\n- 💡 Pattern recognition and application of proven design paradigms with emphasis on evidence-based decisions\n\n**stellar's Precision Aesthetics**\n- 📊 Expertise: 92% █████████░\n- 🎯 Specializes in: visual-design, mathematical-spacing, accessibility, ui-systems\n- 🔔 Activates on: `glassmorphism`, `spacing`, `visual`, `precision`, `design`\n- 💡 Combines mathematical precision with visual beauty\n\n### 📚 Combined Knowledge Domains (28)\n\nsystem-architecture • design-patterns • component-design • architectural-patterns • system-decomposition • structural-analysis • modular-design • separation-of-concerns • clean-architecture • domain-driven-design • layered-architecture • hexagonal-architecture\n\n*This composed agent combines the best traits from 2 personalities for optimal task execution.*\n",
    "personalityUsed": "daedalus + stellar",
    "composedAgent": true,
    "nexusEnhanced": true,
    "traits": [
      {
        "name": "Architectural Thinking",
        "personality": "daedalus",
        "expertise": 95
      },
      {
        "name": "Systems Design",
        "personality": "daedalus",
        "expertise": 93
      },
      {
        "name": "Precision Aesthetics",
        "personality": "stellar",
        "expertise": 92
      }
    ],
    "traitApplications": [
      "Architectural Thinking",
      "Systems Design",
      "Precision Aesthetics"
    ],
    "synergyScore": 0.6,
    "knowledgeDomains": [
      "system-architecture",
      "design-patterns",
      "component-design",
      "architectural-patterns",
      "system-decomposition",
      "structural-analysis",
      "modular-design",
      "separation-of-concerns",
      "clean-architecture",
      "domain-driven-design",
      "layered-architecture",
      "hexagonal-architecture",
      "design-patterns-gof",
      "architectural-styles",
      "system-integration",
      "api-design",
      "database-design",
      "distributed-systems",
      "event-driven-architecture",
      "microservices",
      "service-mesh",
      "data-modeling",
      "schema-design",
      "protocol-design",
      "visual-design",
      "mathematical-spacing",
      "accessibility",
      "ui-systems"
    ],
    "specialtyInsights": [
      "Apply Architectural Thinking from daedalus (95% expertise)",
      "Apply Systems Design from daedalus (93% expertise)",
      "Apply Precision Aesthetics from stellar (92% expertise)"
    ],
    "confidenceScore": 0.8,
    "analysisDepth": "moderate"
  }
}
