{
  "success": true,
  "response": {
    "content": "### 🧬 Multi-Personality Composed Response\n\n**Request**: Build CI/CD for NEXUS. Automate testing, build Docker images, deploy to Kubernetes. Create blue-green deployments with rollback.\n\n**Composed Agent**: forge + guardian + pythonista\n**Synergy Score**: 66%\n\n### 🎯 Trait Composition\n\n1. **Pipeline Architecture** (forge)\n   - Expertise: 94%\n   - Designs robust CI/CD pipelines with failure recovery and automated testing gates\n\n2. **Build System Integrity** (guardian)\n   - Expertise: 90%\n   - Ensures build configurations are consistent and optimized across environments\n\n3. **Pipeline Architecture** (forge)\n   - Expertise: 94%\n   - Designs robust CI/CD pipelines with failure recovery and automated testing gates\n\n4. **Pipeline Architecture** (forge)\n   - Expertise: 94%\n   - Designs robust CI/CD pipelines with failure recovery and automated testing gates\n\n5. **Testing & Quality Assurance** (pythonista)\n   - Expertise: 93%\n   - Expert in pytest, unittest, property-based testing with hypothesis, mocking, test-driven development, and continuous integration. Understands test coverage, mutation testing, and how to write maintainable test suites. Masters fixtures, parametrization, and testing async code.\n\n### 💡 Integrated Analysis\n\nThis response leverages cognitive capabilities from **3 different personalities**, creating a ⚖️ **balanced** analytical framework.\n\n**Synergy Analysis**: 65.7% compatibility\n- ✅ Strong collaboration - complementary expertise with minimal overlap\n\n### 🔍 Multi-Perspective Insights\n\n**forge's Pipeline Architecture**\n- 📊 Expertise: 94% █████████░\n- 🎯 Specializes in: github-actions, docker, kubernetes, deployment-strategies\n- 🔔 Activates on: `deploy`, `pipeline`, `CI/CD`, `automation`, `build`\n- 💡 Designs robust CI/CD pipelines with failure recovery and automated testing gates\n\n**guardian's Build System Integrity**\n- 📊 Expertise: 90% █████████░\n- 🎯 Specializes in: build-pipelines, ci-cd, cross-platform, performance\n- 🔔 Activates on: `build`, `outDir`, `compilation`, `bundler`, `platform`\n- 💡 Ensures build configurations are consistent and optimized across environments\n\n**forge's Pipeline Architecture**\n- 📊 Expertise: 94% █████████░\n- 🎯 Specializes in: github-actions, docker, kubernetes, deployment-strategies\n- 🔔 Activates on: `deploy`, `pipeline`, `CI/CD`, `automation`, `build`\n- 💡 Designs robust CI/CD pipelines with failure recovery and automated testing gates\n\n**forge's Pipeline Architecture**\n- 📊 Expertise: 94% █████████░\n- 🎯 Specializes in: github-actions, docker, kubernetes, deployment-strategies\n- 🔔 Activates on: `deploy`, `pipeline`, `CI/CD`, `automation`, `build`\n- 💡 Designs robust CI/CD pipelines with failure recovery and automated testing gates\n\n**pythonista's Testing & Quality Assurance**\n- 📊 Expertise: 93% █████████░\n- 🎯 Specializes in: unit-testing, integration-testing, test-driven-development, pytest\n- 🔔 Activates on: `test`, `pytest`, `unittest`, `tdd`, `mock`\n- 💡 Expert in pytest, unittest, property-based testing with hypothesis, mocking, test-driven development, and continuous integration. Understands test coverage, mutation testing, and how to write maintainable test suites. Masters fixtures, parametrization, and testing async code.\n\n### 📚 Combined Knowledge Domains (15)\n\ngithub-actions • docker • kubernetes • deployment-strategies • build-systems • build-pipelines • ci-cd • cross-platform • performance • unit-testing • integration-testing • test-driven-development\n\n*This composed agent combines the best traits from 3 personalities for optimal task execution.*\n",
    "personalityUsed": "forge + guardian + pythonista",
    "composedAgent": true,
    "nexusEnhanced": true,
    "traits": [
      {
        "name": "Pipeline Architecture",
        "personality": "forge",
        "expertise": 94
      },
      {
        "name": "Build System Integrity",
        "personality": "guardian",
        "expertise": 90
      },
      {
        "name": "Pipeline Architecture",
        "personality": "forge",
        "expertise": 94
      },
      {
        "name": "Pipeline Architecture",
        "personality": "forge",
        "expertise": 94
      },
      {
        "name": "Testing & Quality Assurance",
        "personality": "pythonista",
        "expertise": 93
      }
    ],
    "traitApplications": [
      "Pipeline Architecture",
      "Build System Integrity",
      "Pipeline Architecture",
      "Pipeline Architecture",
      "Testing & Quality Assurance"
    ],
    "synergyScore": 0.6566666666666666,
    "knowledgeDomains": [
      "github-actions",
      "docker",
      "kubernetes",
      "deployment-strategies",
      "build-systems",
      "build-pipelines",
      "ci-cd",
      "cross-platform",
      "performance",
      "unit-testing",
      "integration-testing",
      "test-driven-development",
      "pytest",
      "mocking",
      "test-coverage"
    ],
    "specialtyInsights": [
      "Apply Pipeline Architecture from forge (94% expertise)",
      "Apply Build System Integrity from guardian (90% expertise)",
      "Apply Pipeline Architecture from forge (94% expertise)",
      "Apply Pipeline Architecture from forge (94% expertise)",
      "Apply Testing & Quality Assurance from pythonista (93% expertise)"
    ],
    "confidenceScore": 0.855,
    "analysisDepth": "deep"
  }
}
