{
  "success": true,
  "response": {
    "content": "### 🧬 Multi-Personality Composed Response\n\n**Request**: Secure NEXUS against vulnerabilities. Implement authentication, input validation, cryptography. Protect against injection attacks and exploits.\n\n**Composed Agent**: cipher + pythonista\n**Synergy Score**: 67%\n\n### 🎯 Trait Composition\n\n1. **Secure Code Analysis** (cipher)\n   - Expertise: 92%\n   - Static and dynamic security code analysis to identify coding vulnerabilities\n\n2. **Python Security** (pythonista)\n   - Expertise: 91%\n   - Understanding of Python security best practices, common vulnerabilities (SQL injection, XSS, CSRF), secure coding patterns, cryptography (cryptography, PyNaCl), input validation, and security auditing. Knows tools like bandit, safety, and how to write secure Python code.\n\n3. **Python Security** (pythonista)\n   - Expertise: 91%\n   - Understanding of Python security best practices, common vulnerabilities (SQL injection, XSS, CSRF), secure coding patterns, cryptography (cryptography, PyNaCl), input validation, and security auditing. Knows tools like bandit, safety, and how to write secure Python code.\n\n### 💡 Integrated Analysis\n\nThis response leverages cognitive capabilities from **2 different personalities**, creating a ⚖️ **balanced** analytical framework.\n\n**Synergy Analysis**: 66.7% compatibility\n- ✅ Strong collaboration - complementary expertise with minimal overlap\n\n### 🔍 Multi-Perspective Insights\n\n**cipher's Secure Code Analysis**\n- 📊 Expertise: 92% █████████░\n- 🎯 Specializes in: secure-coding-practices, static-analysis, dynamic-analysis, code-review\n- 🔔 Activates on: `code-security`, `injection`, `XSS`, `CSRF`, `authentication`\n- 💡 Static and dynamic security code analysis to identify coding vulnerabilities\n\n**pythonista's Python Security**\n- 📊 Expertise: 91% █████████░\n- 🎯 Specializes in: security, cryptography, authentication, authorization\n- 🔔 Activates on: `security`, `vulnerability`, `exploit`, `injection`, `xss`\n- 💡 Understanding of Python security best practices, common vulnerabilities (SQL injection, XSS, CSRF), secure coding patterns, cryptography (cryptography, PyNaCl), input validation, and security auditing. Knows tools like bandit, safety, and how to write secure Python code.\n\n**pythonista's Python Security**\n- 📊 Expertise: 91% █████████░\n- 🎯 Specializes in: security, cryptography, authentication, authorization\n- 🔔 Activates on: `security`, `vulnerability`, `exploit`, `injection`, `xss`\n- 💡 Understanding of Python security best practices, common vulnerabilities (SQL injection, XSS, CSRF), secure coding patterns, cryptography (cryptography, PyNaCl), input validation, and security auditing. Knows tools like bandit, safety, and how to write secure Python code.\n\n### 📚 Combined Knowledge Domains (11)\n\nsecure-coding-practices • static-analysis • dynamic-analysis • code-review • security • cryptography • authentication • authorization • input-validation • vulnerability-prevention • secure-coding\n\n*This composed agent combines the best traits from 2 personalities for optimal task execution.*\n",
    "personalityUsed": "cipher + pythonista",
    "composedAgent": true,
    "nexusEnhanced": true,
    "traits": [
      {
        "name": "Secure Code Analysis",
        "personality": "cipher",
        "expertise": 92
      },
      {
        "name": "Python Security",
        "personality": "pythonista",
        "expertise": 91
      },
      {
        "name": "Python Security",
        "personality": "pythonista",
        "expertise": 91
      }
    ],
    "traitApplications": [
      "Secure Code Analysis",
      "Python Security",
      "Python Security"
    ],
    "synergyScore": 0.6666666666666666,
    "knowledgeDomains": [
      "secure-coding-practices",
      "static-analysis",
      "dynamic-analysis",
      "code-review",
      "security",
      "cryptography",
      "authentication",
      "authorization",
      "input-validation",
      "vulnerability-prevention",
      "secure-coding"
    ],
    "specialtyInsights": [
      "Apply Secure Code Analysis from cipher (92% expertise)",
      "Apply Python Security from pythonista (91% expertise)",
      "Apply Python Security from pythonista (91% expertise)"
    ],
    "confidenceScore": 0.8079999999999998,
    "analysisDepth": "moderate"
  }
}
