{
  "success": true,
  "response": {
    "content": "### ğŸ§¬ Multi-Personality Composed Response\n\n**Request**: Connect NEXUS to everything - APIs, webhooks, message queues, databases. Build middleware, ESB patterns, event streaming.\n\n**Composed Agent**: forge + guardian\n**Synergy Score**: 50%\n\n### ğŸ¯ Trait Composition\n\n1. **Pipeline Architecture** (forge)\n   - Expertise: 94%\n   - Designs robust CI/CD pipelines with failure recovery and automated testing gates\n\n2. **Build System Integrity** (guardian)\n   - Expertise: 90%\n   - Ensures build configurations are consistent and optimized across environments\n\n### ğŸ’¡ Integrated Analysis\n\nThis response leverages cognitive capabilities from **2 different personalities**, creating a âš–ï¸ **balanced** analytical framework.\n\n**Synergy Analysis**: 50.0% compatibility\n- ğŸ”„ Moderate synergy - diverse perspectives with some coordination needed\n\n### ğŸ” Multi-Perspective Insights\n\n**forge's Pipeline Architecture**\n- ğŸ“Š Expertise: 94% â–ˆâ–ˆâ–ˆâ–ˆâ–ˆâ–ˆâ–ˆâ–ˆâ–ˆâ–‘\n- ğŸ¯ Specializes in: github-actions, docker, kubernetes, deployment-strategies\n- ğŸ”” Activates on: `deploy`, `pipeline`, `CI/CD`, `automation`, `build`\n- ğŸ’¡ Designs robust CI/CD pipelines with failure recovery and automated testing gates\n\n**guardian's Build System Integrity**\n- ğŸ“Š Expertise: 90% â–ˆâ–ˆâ–ˆâ–ˆâ–ˆâ–ˆâ–ˆâ–ˆâ–ˆâ–‘\n- ğŸ¯ Specializes in: build-pipelines, ci-cd, cross-platform, performance\n- ğŸ”” Activates on: `build`, `outDir`, `compilation`, `bundler`, `platform`\n- ğŸ’¡ Ensures build configurations are consistent and optimized across environments\n\n### ğŸ“š Combined Knowledge Domains (9)\n\ngithub-actions â€¢ docker â€¢ kubernetes â€¢ deployment-strategies â€¢ build-systems â€¢ build-pipelines â€¢ ci-cd â€¢ cross-platform â€¢ performance\n\n*This composed agent combines the best traits from 2 personalities for optimal task execution.*\n",
    "personalityUsed": "forge + guardian",
    "composedAgent": true,
    "nexusEnhanced": true,
    "traits": [
      {
        "name": "Pipeline Architecture",
        "personality": "forge",
        "expertise": 94
      },
      {
        "name": "Build System Integrity",
        "personality": "guardian",
        "expertise": 90
      }
    ],
    "traitApplications": [
      "Pipeline Architecture",
      "Build System Integrity"
    ],
    "synergyScore": 0.5,
    "knowledgeDomains": [
      "github-actions",
      "docker",
      "kubernetes",
      "deployment-strategies",
      "build-systems",
      "build-pipelines",
      "ci-cd",
      "cross-platform",
      "performance"
    ],
    "specialtyInsights": [
      "Apply Pipeline Architecture from forge (94% expertise)",
      "Apply Build System Integrity from guardian (90% expertise)"
    ],
    "confidenceScore": 0.7420000000000001,
    "analysisDepth": "moderate"
  }
}
