{
  "success": true,
  "response": {
    "content": "### üß¨ Multi-Personality Composed Response\n\n**Request**: Profile NEXUS performance. Measure latency, throughput, memory usage. Optimize hot paths, implement caching, reduce overhead.\n\n**Composed Agent**: flash + pythonista + promptcrafter\n**Synergy Score**: 54%\n\n### üéØ Trait Composition\n\n1. **Performance Optimization** (pythonista)\n   - Expertise: 96%\n   - Deep knowledge of Python performance optimization, profiling, and bottleneck elimination. Understands CPython internals, JIT compilation with PyPy, Cython for C extensions, NumPy vectorization, and when to drop to C. Masters memory profiling, algorithmic optimization, and caching strategies.\n\n2. **Performance Optimization** (pythonista)\n   - Expertise: 96%\n   - Deep knowledge of Python performance optimization, profiling, and bottleneck elimination. Understands CPython internals, JIT compilation with PyPy, Cython for C extensions, NumPy vectorization, and when to drop to C. Masters memory profiling, algorithmic optimization, and caching strategies.\n\n3. **Iterative Refinement** (promptcrafter)\n   - Expertise: 93%\n   - Systematically improving prompts through testing, analyzing results, and making targeted adjustments for optimal outcomes\n\n### üí° Integrated Analysis\n\nThis response leverages cognitive capabilities from **3 different personalities**, creating a ‚öñÔ∏è **balanced** analytical framework.\n\n**Synergy Analysis**: 54.4% compatibility\n- üîÑ Moderate synergy - diverse perspectives with some coordination needed\n\n### üîç Multi-Perspective Insights\n\n**pythonista's Performance Optimization**\n- üìä Expertise: 96% ‚ñà‚ñà‚ñà‚ñà‚ñà‚ñà‚ñà‚ñà‚ñà‚ñë\n- üéØ Specializes in: performance-tuning, profiling, cpython-internals, cython\n- üîî Activates on: `performance`, `optimization`, `speed`, `slow`, `bottleneck`\n- üí° Deep knowledge of Python performance optimization, profiling, and bottleneck elimination. Understands CPython internals, JIT compilation with PyPy, Cython for C extensions, NumPy vectorization, and when to drop to C. Masters memory profiling, algorithmic optimization, and caching strategies.\n\n**pythonista's Performance Optimization**\n- üìä Expertise: 96% ‚ñà‚ñà‚ñà‚ñà‚ñà‚ñà‚ñà‚ñà‚ñà‚ñë\n- üéØ Specializes in: performance-tuning, profiling, cpython-internals, cython\n- üîî Activates on: `performance`, `optimization`, `speed`, `slow`, `bottleneck`\n- üí° Deep knowledge of Python performance optimization, profiling, and bottleneck elimination. Understands CPython internals, JIT compilation with PyPy, Cython for C extensions, NumPy vectorization, and when to drop to C. Masters memory profiling, algorithmic optimization, and caching strategies.\n\n**promptcrafter's Iterative Refinement**\n- üìä Expertise: 93% ‚ñà‚ñà‚ñà‚ñà‚ñà‚ñà‚ñà‚ñà‚ñà‚ñë\n- üéØ Specializes in: prompt-iteration, result-analysis, systematic-improvement\n- üîî Activates on: `refine`, `improve`, `iterate`, `optimize`, `enhance prompt`\n- üí° Systematically improving prompts through testing, analyzing results, and making targeted adjustments for optimal outcomes\n\n### üìö Combined Knowledge Domains (11)\n\nperformance-tuning ‚Ä¢ profiling ‚Ä¢ cpython-internals ‚Ä¢ cython ‚Ä¢ numpy ‚Ä¢ algorithmic-optimization ‚Ä¢ memory-management ‚Ä¢ caching ‚Ä¢ prompt-iteration ‚Ä¢ result-analysis ‚Ä¢ systematic-improvement\n\n*This composed agent combines the best traits from 3 personalities for optimal task execution.*\n",
    "personalityUsed": "flash + pythonista + promptcrafter",
    "composedAgent": true,
    "nexusEnhanced": true,
    "traits": [
      {
        "name": "Performance Optimization",
        "personality": "pythonista",
        "expertise": 96
      },
      {
        "name": "Performance Optimization",
        "personality": "pythonista",
        "expertise": 96
      },
      {
        "name": "Iterative Refinement",
        "personality": "promptcrafter",
        "expertise": 93
      }
    ],
    "traitApplications": [
      "Performance Optimization",
      "Performance Optimization",
      "Iterative Refinement"
    ],
    "synergyScore": 0.5444444444444444,
    "knowledgeDomains": [
      "performance-profiling",
      "memory-management",
      "caching",
      "resource-optimization",
      "performance-tuning",
      "profiling",
      "cpython-internals",
      "cython",
      "numpy",
      "algorithmic-optimization",
      "prompt-iteration",
      "result-analysis",
      "systematic-improvement"
    ],
    "specialtyInsights": [
      "Apply Performance Optimization from pythonista (96% expertise)",
      "Apply Performance Optimization from pythonista (96% expertise)",
      "Apply Iterative Refinement from promptcrafter (93% expertise)"
    ],
    "confidenceScore": 0.7933333333333332,
    "analysisDepth": "moderate"
  }
}
