{
  "success": true,
  "response": {
    "content": "### 🧬 Multi-Personality Composed Response\n\n**Request**: Optimize NEXUS Python code for maximum speed. Profile bottlenecks, implement Cython extensions, use async/await patterns. Make it blazing fast.\n\n**Composed Agent**: pythonista + promptcrafter\n**Synergy Score**: 60%\n\n### 🎯 Trait Composition\n\n1. **Pythonic Thinking** (pythonista)\n   - Expertise: 98%\n   - Deep understanding of Python philosophy, idioms, and best practices. Writes code that's not just correct but beautiful, readable, and maintainable. Knows when to use list comprehensions vs generators, when to leverage duck typing, and how to make code truly Pythonic.\n\n2. **Performance Optimization** (pythonista)\n   - Expertise: 96%\n   - Deep knowledge of Python performance optimization, profiling, and bottleneck elimination. Understands CPython internals, JIT compilation with PyPy, Cython for C extensions, NumPy vectorization, and when to drop to C. Masters memory profiling, algorithmic optimization, and caching strategies.\n\n3. **Iterative Refinement** (promptcrafter)\n   - Expertise: 93%\n   - Systematically improving prompts through testing, analyzing results, and making targeted adjustments for optimal outcomes\n\n### 💡 Integrated Analysis\n\nThis response leverages cognitive capabilities from **2 different personalities**, creating a ⚖️ **balanced** analytical framework.\n\n**Synergy Analysis**: 60.0% compatibility\n- ✅ Strong collaboration - complementary expertise with minimal overlap\n\n### 🔍 Multi-Perspective Insights\n\n**pythonista's Pythonic Thinking**\n- 📊 Expertise: 98% █████████░\n- 🎯 Specializes in: python-philosophy, code-style, idioms, best-practices\n- 🔔 Activates on: `python`, `pythonic`, `idiomatic`, `pep8`, `zen of python`\n- 💡 Deep understanding of Python philosophy, idioms, and best practices. Writes code that's not just correct but beautiful, readable, and maintainable. Knows when to use list comprehensions vs generators, when to leverage duck typing, and how to make code truly Pythonic.\n\n**pythonista's Performance Optimization**\n- 📊 Expertise: 96% █████████░\n- 🎯 Specializes in: performance-tuning, profiling, cpython-internals, cython\n- 🔔 Activates on: `performance`, `optimization`, `speed`, `slow`, `bottleneck`\n- 💡 Deep knowledge of Python performance optimization, profiling, and bottleneck elimination. Understands CPython internals, JIT compilation with PyPy, Cython for C extensions, NumPy vectorization, and when to drop to C. Masters memory profiling, algorithmic optimization, and caching strategies.\n\n**promptcrafter's Iterative Refinement**\n- 📊 Expertise: 93% █████████░\n- 🎯 Specializes in: prompt-iteration, result-analysis, systematic-improvement\n- 🔔 Activates on: `refine`, `improve`, `iterate`, `optimize`, `enhance prompt`\n- 💡 Systematically improving prompts through testing, analyzing results, and making targeted adjustments for optimal outcomes\n\n### 📚 Combined Knowledge Domains (17)\n\npython-philosophy • code-style • idioms • best-practices • readability • maintainability • performance-tuning • profiling • cpython-internals • cython • numpy • algorithmic-optimization\n\n*This composed agent combines the best traits from 2 personalities for optimal task execution.*\n",
    "personalityUsed": "pythonista + promptcrafter",
    "composedAgent": true,
    "nexusEnhanced": true,
    "traits": [
      {
        "name": "Pythonic Thinking",
        "personality": "pythonista",
        "expertise": 98
      },
      {
        "name": "Performance Optimization",
        "personality": "pythonista",
        "expertise": 96
      },
      {
        "name": "Iterative Refinement",
        "personality": "promptcrafter",
        "expertise": 93
      }
    ],
    "traitApplications": [
      "Pythonic Thinking",
      "Performance Optimization",
      "Iterative Refinement"
    ],
    "synergyScore": 0.6,
    "knowledgeDomains": [
      "python-philosophy",
      "code-style",
      "idioms",
      "best-practices",
      "readability",
      "maintainability",
      "performance-tuning",
      "profiling",
      "cpython-internals",
      "cython",
      "numpy",
      "algorithmic-optimization",
      "memory-management",
      "caching",
      "prompt-iteration",
      "result-analysis",
      "systematic-improvement"
    ],
    "specialtyInsights": [
      "Apply Pythonic Thinking from pythonista (98% expertise)",
      "Apply Performance Optimization from pythonista (96% expertise)",
      "Apply Iterative Refinement from promptcrafter (93% expertise)"
    ],
    "confidenceScore": 0.8140000000000001,
    "analysisDepth": "moderate"
  }
}
