{
  "success": true,
  "response": {
    "content": "### üß¨ Multi-Personality Composed Response\n\n**Request**: Analyze the impact of installing these VS Code extensions on NEXUS development capabilities: Jupyter Notebooks, REST Client, Data Wrangler, Coverage Gutters, PostgreSQL, MongoDB, Redis Explorer, Python Test Explorer, Todo Tree, Pylint, Black Formatter, IntelliCode, Thunder Client, Markdown All in One. Explain specifically: (1) How each tool enhances NEXUS development, (2) What new capabilities we gain, (3) Performance improvements expected, (4) Development workflow improvements, (5) Which extensions synergize best together. Be specific and technical.\n\n**Composed Agent**: pythonista + flash + hunter\n**Synergy Score**: 60%\n\n### üéØ Trait Composition\n\n1. **Pythonic Thinking** (pythonista)\n   - Expertise: 98%\n   - Deep understanding of Python philosophy, idioms, and best practices. Writes code that's not just correct but beautiful, readable, and maintainable. Knows when to use list comprehensions vs generators, when to leverage duck typing, and how to make code truly Pythonic.\n\n2. **Performance Optimization** (pythonista)\n   - Expertise: 96%\n   - Deep knowledge of Python performance optimization, profiling, and bottleneck elimination. Understands CPython internals, JIT compilation with PyPy, Cython for C extensions, NumPy vectorization, and when to drop to C. Masters memory profiling, algorithmic optimization, and caching strategies.\n\n3. **Performance Optimization** (pythonista)\n   - Expertise: 96%\n   - Deep knowledge of Python performance optimization, profiling, and bottleneck elimination. Understands CPython internals, JIT compilation with PyPy, Cython for C extensions, NumPy vectorization, and when to drop to C. Masters memory profiling, algorithmic optimization, and caching strategies.\n\n4. **Forensic Analysis** (hunter)\n   - Expertise: 95%\n   - Evidence-based verification of technical claims with brutal honesty about limitations\n\n5. **Data Science & ML Engineering** (pythonista)\n   - Expertise: 95%\n   - Expertise in Python's data science ecosystem: pandas, NumPy, scikit-learn, PyTorch, TensorFlow, Jupyter. Understands data pipelines, feature engineering, model training, and deployment. Can architect ML systems from experimentation to production.\n\n### üí° Integrated Analysis\n\nThis response leverages cognitive capabilities from **3 different personalities**, creating a ‚öñÔ∏è **balanced** analytical framework.\n\n**Synergy Analysis**: 60.3% compatibility\n- ‚úÖ Strong collaboration - complementary expertise with minimal overlap\n\n### üîç Multi-Perspective Insights\n\n**pythonista's Pythonic Thinking**\n- üìä Expertise: 98% ‚ñà‚ñà‚ñà‚ñà‚ñà‚ñà‚ñà‚ñà‚ñà‚ñë\n- üéØ Specializes in: python-philosophy, code-style, idioms, best-practices\n- üîî Activates on: `python`, `pythonic`, `idiomatic`, `pep8`, `zen of python`\n- üí° Deep understanding of Python philosophy, idioms, and best practices. Writes code that's not just correct but beautiful, readable, and maintainable. Knows when to use list comprehensions vs generators, when to leverage duck typing, and how to make code truly Pythonic.\n\n**pythonista's Performance Optimization**\n- üìä Expertise: 96% ‚ñà‚ñà‚ñà‚ñà‚ñà‚ñà‚ñà‚ñà‚ñà‚ñë\n- üéØ Specializes in: performance-tuning, profiling, cpython-internals, cython\n- üîî Activates on: `performance`, `optimization`, `speed`, `slow`, `bottleneck`\n- üí° Deep knowledge of Python performance optimization, profiling, and bottleneck elimination. Understands CPython internals, JIT compilation with PyPy, Cython for C extensions, NumPy vectorization, and when to drop to C. Masters memory profiling, algorithmic optimization, and caching strategies.\n\n**pythonista's Performance Optimization**\n- üìä Expertise: 96% ‚ñà‚ñà‚ñà‚ñà‚ñà‚ñà‚ñà‚ñà‚ñà‚ñë\n- üéØ Specializes in: performance-tuning, profiling, cpython-internals, cython\n- üîî Activates on: `performance`, `optimization`, `speed`, `slow`, `bottleneck`\n- üí° Deep knowledge of Python performance optimization, profiling, and bottleneck elimination. Understands CPython internals, JIT compilation with PyPy, Cython for C extensions, NumPy vectorization, and when to drop to C. Masters memory profiling, algorithmic optimization, and caching strategies.\n\n**hunter's Forensic Analysis**\n- üìä Expertise: 95% ‚ñà‚ñà‚ñà‚ñà‚ñà‚ñà‚ñà‚ñà‚ñà‚ñë\n- üéØ Specializes in: testing, debugging, security, performance-analysis\n- üîî Activates on: `audit`, `verify`, `evidence`, `proof`, `gap`\n- üí° Evidence-based verification of technical claims with brutal honesty about limitations\n\n**pythonista's Data Science & ML Engineering**\n- üìä Expertise: 95% ‚ñà‚ñà‚ñà‚ñà‚ñà‚ñà‚ñà‚ñà‚ñà‚ñë\n- üéØ Specializes in: data-analysis, machine-learning, deep-learning, data-pipelines\n- üîî Activates on: `data`, `pandas`, `numpy`, `machine learning`, `ml`\n- üí° Expertise in Python's data science ecosystem: pandas, NumPy, scikit-learn, PyTorch, TensorFlow, Jupyter. Understands data pipelines, feature engineering, model training, and deployment. Can architect ML systems from experimentation to production.\n\n### üìö Combined Knowledge Domains (29)\n\npython-philosophy ‚Ä¢ code-style ‚Ä¢ idioms ‚Ä¢ best-practices ‚Ä¢ readability ‚Ä¢ maintainability ‚Ä¢ performance-tuning ‚Ä¢ profiling ‚Ä¢ cpython-internals ‚Ä¢ cython ‚Ä¢ numpy ‚Ä¢ algorithmic-optimization\n\n*This composed agent combines the best traits from 3 personalities for optimal task execution.*\n",
    "personalityUsed": "pythonista + flash + hunter",
    "composedAgent": true,
    "nexusEnhanced": true,
    "traits": [
      {
        "name": "Pythonic Thinking",
        "personality": "pythonista",
        "expertise": 98
      },
      {
        "name": "Performance Optimization",
        "personality": "pythonista",
        "expertise": 96
      },
      {
        "name": "Performance Optimization",
        "personality": "pythonista",
        "expertise": 96
      },
      {
        "name": "Forensic Analysis",
        "personality": "hunter",
        "expertise": 95
      },
      {
        "name": "Data Science & ML Engineering",
        "personality": "pythonista",
        "expertise": 95
      }
    ],
    "traitApplications": [
      "Pythonic Thinking",
      "Performance Optimization",
      "Performance Optimization",
      "Forensic Analysis",
      "Data Science & ML Engineering"
    ],
    "synergyScore": 0.6033333333333333,
    "knowledgeDomains": [
      "python-philosophy",
      "code-style",
      "idioms",
      "best-practices",
      "readability",
      "maintainability",
      "performance-profiling",
      "memory-management",
      "caching",
      "resource-optimization",
      "performance-tuning",
      "profiling",
      "cpython-internals",
      "cython",
      "numpy",
      "algorithmic-optimization",
      "testing",
      "debugging",
      "security",
      "performance-analysis",
      "root-cause-analysis",
      "failure-analysis",
      "incident-investigation",
      "diagnostic-techniques",
      "data-analysis",
      "machine-learning",
      "deep-learning",
      "data-pipelines",
      "feature-engineering",
      "model-deployment",
      "mlops"
    ],
    "specialtyInsights": [
      "Apply Pythonic Thinking from pythonista (98% expertise)",
      "Apply Performance Optimization from pythonista (96% expertise)",
      "Apply Performance Optimization from pythonista (96% expertise)",
      "Apply Forensic Analysis from hunter (95% expertise)",
      "Apply Data Science & ML Engineering from pythonista (95% expertise)"
    ],
    "confidenceScore": 0.8569999999999999,
    "analysisDepth": "deep"
  }
}
